[
  {
    "title": "נהג המסיע נוסע במושב האחורי לא חגור",
    "symbol": 6004,
    "severity": "***",
    "type": "ביד\"ץ",
    "description": "נהגת ברכב הנ\"ל שהיו מותקנות בו, והנחת לנוסע/ים לשבת במושב האחורי של הרכב, בלי שהיה/היו חגור/ים בחגורות בטיחות, בניגוד לתקנה 83ב(א) לתקנות התעבורה",
    "id": "68767fb6f099c55c06e2c529"
  },
  {
    "title": "נוסע במושב האחורי לא חגור",
    "symbol": 6000,
    "severity": "***",
    "type": "ביד\"ץ",
    "description": "נסעת ברכב הנ\"ל שהיו מותקנות בו חגורות בטיחות, במושב האחורי, מבלי שהיית חגור בחגורות בטיחות, בניגוד לתקנה 83(ב) לתקנות התעבורה",
    "id": "6876829bf099c55c06e2c52a"
  },
  {
    "title": "נהג ללא חגורת בטיחות",
    "symbol": 6001,
    "severity": "***",
    "type": "ביד\"ץ",
    "description": "נהגת ברכב הנ\"ל שהיו מותקנות בו חגורות בטיחות, מבלי שהיית חגור בחגורת בטיחות, בניגוד לתקנה 83ב(א) לתקנות התעבורה",
    "id": "68768323f099c55c06e2c52b"
  },
  {
    "title": "אי ציות לתמרור 302 - עצור",
    "symbol": 6200,
    "severity": "***",
    "type": "ביד\"ץ",
    "description": "נהגת ברכב הנ\"ל ולא ציית לתמרור 302 המוצב בדרך בכיוון נסיעתך, בכך שלא עצרת את רכבך לפני קו העצירה/במקום בו ניתן לראות את התנועה בדרך החוצה, בניגוד לתקנה 64(ד)+22(א) לתקנות התעבורה",
    "id": "6876856bf099c55c06e2c52c"
  },
  {
    "title": "אי ציות לתמרור 302 צומת - עצור וזכות קדימה",
    "symbol": 6202,
    "severity": "***",
    "type": "ביד\"ץ + התליה",
    "description": "נהגת ברכב הנ\"ל, ולא ציית לתמרור 302 המוצב בדרך בכיוון נסיעתך, בכך שלא עצרת כדין את רכבך ולא נתת זכות קדימה לכלי הרכב הבא או הנכנס אל הצומת, בניגוד לתקנה 64(ד)+22(א) לתקנות התעבורה",
    "id": "68768671f099c55c06e2c52d"
  },
  {
    "title": "שימוש בטלפון בעת שהרכב נע שלא באמצעות מיקרופון המותקן ברכב",
    "symbol": 6300,
    "severity": "***",
    "type": "ביד\"ץ",
    "description": "נהגת ברכב הנ\"ל, ובעת שהרכב היה בתנועה השתמשת בטלפון קבוע/נייד שלא באמצעות דיבורית בניגוד לתקנה 28(ב) לתקנות התעבורה",
    "id": "68768817f099c55c06e2c52e"
  },
  {
    "title": "אי התקנת שתי לוחיות זיהוי",
    "symbol": 6229,
    "severity": "**",
    "type": "דמ\"ש",
    "description": "נהגת ברכב הנ\"ל, הרשום בישראל, כשאין הוא נושא עליו לוחית זיהוי, בניגוד לתקנה 165(ב) לתקנות התעבורה",
    "id": "6876894cf099c55c06e2c530"
  },
  {
    "title": "נהיגה בחוסר זהירות",
    "symbol": 6392,
    "severity": "**",
    "type": "ביד\"ץ",
    "description": "נהגת ברכב הנ\"ל בלא זהירות בכך ש... (פרט) את מעשה הנהג, בניגוד לתקנה 21(ג) לתקנות התעבורה",
    "id": "6876897af099c55c06e2c532"
  },
  {
    "title": "אי ציות לתמרור 402 - איסור הכניסה לכל רכב",
    "symbol": 6205,
    "severity": "***",
    "type": "ביד\"ץ + התליה",
    "description": "נהגת ברכב הנ\"ל ולא ציית לתמרור 402 המוצב במקום, בכך שנכנסת לדרך שלא בהתאם להוראות התמרור הנ\"ל בניגוד לתקנה 22 (א) לתקנות התעבורה",
    "id": "687689e2f099c55c06e2c533"
  },
  {
    "title": "מגב/ים לא תקין/ים",
    "symbol": 6285,
    "severity": "*",
    "type": "דמ\"ש",
    "description": "נהגת ברכב הנ\"ל, שהינו בעל שימשה קדמית בו היה/היו מותקן/נים בלתי תקין/נים, בניגוד לתקנה 357 (א) לתקנות התעבורה",
    "id": "687c94aaad11489565e6a0ed"
  },
  {
    "title": "אי הצבת משולש אזהרה מאחורי רכב עומד",
    "symbol": 6409,
    "severity": "**",
    "type": "דמ\"ש",
    "description": "נהגת ברכב הנ\"ל, שנעצר על פני הדרך מחמת קלקול, ולא הצבת מאחוריו משולש אזהרה, בניגוד לתקנה 70 (א) לתקנות התעבורה",
    "id": "687c9539ad11489565e6a0ee"
  },
  {
    "title": "הפעלת צופר זמן ממושך מן הדרוש",
    "symbol": 6682,
    "severity": "*",
    "type": "דמ\"ש",
    "description": "נהגת ברכב הנ\"ל והשתמשת בצופר זמן ממושך מן הדרוש לפי הנסיבות, בניגוד לתקנה 63 (א) לתקנות התעבורה",
    "id": "687c95a8ad11489565e6a0ef"
  },
  {
    "title": "הפעלת צופר בדרך עיונית",
    "symbol": 6681,
    "severity": "*",
    "type": "דמ\"ש",
    "description": "נהגת ברכב הנ\"ל בדרך עירונית והפעלת צופר שלא לשם מניעת סכנה קרובה, בניגוד לתקנה 63 (ג) לתקנות התעבורה",
    "id": "687c9613ad11489565e6a0f1"
  },
  {
    "title": "הפצת אור מהבהב צבעוני מבלי שהדבר דרוש",
    "symbol": 6680,
    "severity": "**",
    "type": "דמ\"ש",
    "description": "נהגת ברכב הנ\"ל והפצת אור מהבהב צבעוני מבלי שהדבר היה דרוש למילוי התפקיד שהוטל עליך/שלא בשעת מילוי תפקיד המוטל עליך/שלא בעת גרירה וחילוץ בפועל בניגוד לתקנה 62 (ג) לתקנות התעבורה",
    "id": "687c968ead11489565e6a0f2"
  },
  {
    "title": "פתיחת דלתות בזמן הנסיעה על-ידי הנהג",
    "symbol": 6361,
    "severity": "**",
    "type": "דמ\"ש",
    "description": "פתחת את הדלת של האוטובוס הנ\"ל, בזמן נסיעה, בניגוד לתקנה 62 (ג) לתקנות התעבורה",
    "id": "687c9739ad11489565e6a0f3"
  },
  {
    "title": "מערכת אורות בלתי תקינה",
    "symbol": 6695,
    "severity": "**",
    "type": "ביד\"ץ",
    "description": "נהגת ברכב הנ\"ל, כשמערכת האורות שבו אינה מותקנת/אינה פועלת כהלעה, בניגוד לתקנה 96 לתקנות התעבורה",
    "note": "(מדבר על רכב חום + ליסינג)",
    "id": "687c97e1ad11489565e6a0f4"
  },
  {
    "title": "פנס/י חזית/פנס ימני/שמאלי אינו מאיר/ים",
    "symbol": 6077,
    "severity": "*",
    "type": "דמ\"ש",
    "description": "נהגת ברכב הנ\"ל בזמן תאורה כשפנס/י חזית פנס ימני/שמאלי אינו/ם מאיר/ים, בניגוד לתקנה 97 (א) לתקנות התעבורה",
    "id": "687c98d4ad11489565e6a0f6"
  },
  {
    "title": "צבע האורות בפני החזית אינו שווה",
    "symbol": 6694,
    "severity": "*",
    "type": "דמ\"ש",
    "description": "נהגת ברכב הנ\"ל בזמן תאורה, כשצבע האורות בפנסי החזית שלו אינו שווה, בניגוד לתקנה 335 לתקנות התעבורה",
    "id": "687c996ead11489565e6a0f7"
  },
  {
    "title": "אורות חורף דרך עירונית (1 בנובמר עד 31 במרץ)",
    "symbol": 6693,
    "severity": "*",
    "type": "דמ\"ש",
    "description": "נהגת ברכב הנ\"ל שהינו מונית/אוטובוס/רכב מנועי מסחרי שמשקלו הכולל המותר עולה על 14,999 ק\"ג, בדרך עירונית, בלא שפנסי החזית ופנסים אחורים מאירים, בניגוד לתקנה 97 (ג) לתקנות התעבורה",
    "id": "687c99c1ad11489565e6a0f8"
  },
  {
    "title": "אורות חורף (1 בנובמבר עד 31 במרץ) דרך שאינה עירונית (כולל אופנוע)",
    "symbol": 6692,
    "severity": "**",
    "type": "דמ\"ש",
    "description": "נהגת ברכב הנ\"ל בדרך שאינה עירונית, בלא שפנסי החזית ופנסים אחוריים מאירים, בניגוד לתקנה 97 (ג) לתקנות התעבורה",
    "id": "687fdb1f759470e220452e47"
  },
  {
    "title": "נהיגה ללא אורות - אופנוע",
    "symbol": 6691,
    "severity": "**",
    "type": "דמ\"ש",
    "description": "נהגת באופנוע הנ\"ל בדרך כשלא מאירים בו פנסי החזית או הפנסים המיועדים בלעדית לנסיעה ביום, בניגוד לתקנה 97 (ב) לתקנות התעבורה",
    "id": "687fdc0d759470e220452e49"
  },
  {
    "title": "הפנס/ים האחורי/ים אינו/ם מאיר/ים",
    "symbol": 6077,
    "severity": "*",
    "type": "דמ\"ש",
    "description": "נהגת ברכב הנ\"ל בזמן תאורה, כשהפנס האחורי שלו אינו מאיר, בניגוד לתקנה 97 (א) לתקנות התעבורה",
    "id": "687fdc76759470e220452e4a"
  },
  {
    "title": "מכונה ניידת או נגררת, ללא אורות",
    "symbol": 6351,
    "severity": "*",
    "type": "דמ\"ש",
    "description": "הסעת מכונה ניידת/גררת מכונה נגררת, בזמן תאורה, מבלי שהיה קבוע לה מאחור, מצד שמאל, מחזירור בצבע אדום או פנס המפיץ אור אדום והנראה לעין ממרחק של 150 מטר, בניגוד לתקנה 105 לתקנות התעבורה",
    "id": "687fdd25759470e220452e4b"
  },
  {
    "title": "פנס הבלימה אינו תקין",
    "symbol": 6081,
    "severity": "*",
    "type": "דמ\"ש",
    "description": "נהגת ברכב הנ\"ל, כשפנס/ים הבלימה שלו אינו/ם תקין/ים, בניגוד לתקנה 351 (א) לתקנות התעבורה",
    "id": "687fddb5759470e220452e4c"
  },
  {
    "title": "לוחית הזיהוי האחורית אינה מוארת",
    "symbol": 6690,
    "severity": "*",
    "type": "דמ\"ש",
    "description": "נהגת ברכב הנ\"ל בזמן תאורה, כשלוחית הזיהוי האחורית שלו אינה מוארת, בניגוד לתקנה 97 (א) לתקנות התעבורה",
    "note": "ישנם רכבים ללא מערכת האותות, לא יוגש דו\"ח",
    "id": "687fde3c759470e220452e4d"
  },
  {
    "title": "שימוש בזרקור",
    "symbol": 6689,
    "severity": "*",
    "type": "דמ\"ש",
    "description": "נהגת ברכב הנ\"ל והשתמשת בזרקור, כשאורו מופנה לאורך הדרך/למול פני רכב אחר, בניגוד לתקנה 107 (ג) לתקנות התעבורה",
    "id": "687fdeb8759470e220452e4e"
  },
  {
    "title": "מתקן מפיץ אור ברכב ארוך או רחב במידותיו",
    "symbol": 6688,
    "severity": "*",
    "type": "דמ\"ש",
    "description": "נהגת ברכב הנ\"ל, כשאורכו הכולל עם מטען או בלעדיו עולה על 20 מטר ו/או רוחבו עולה על 3 מטר/רכב ולא ליווי כאמור בתקנה 85 (ו) מבלי שהיה מותקן על גג תא הנהג מתקן המפיץ אור צהוב מהבהב, שאורו נראה לכל עוברי דרך מכל הכיוונים, בניגוד לתקנה 101 לתקנות התעבורה",
    "id": "687fdf13759470e220452e4f"
  },
  {
    "title": "שימוש בפנסי ערפל",
    "symbol": 6366,
    "severity": "*",
    "type": "דמ\"ש",
    "description": "נהגת ברכב הנ\"ל והפעלת פנסי ערפל, כשלא היה ערפל ולא ירד גשם שוטף או שלג, בניגוד לתקנה 107 (ד) לתקנות התעבורה",
    "id": "687fdfea759470e220452e50"
  },
  {
    "title": "אי עמעום אור הדרך בנסיעה לקראת הרכב",
    "symbol": 6367,
    "severity": "*",
    "type": "דמ\"ש",
    "description": "נהגת ברכב הנ\"ל בזמן תאורה, ולא עמעמת את אור הדרך כשנסעת לקראת רכב אחר באותה דרך/בדרך סמוכה, בניגוד לתקנה 99(א)(1) לתקנות התעבורה",
    "id": "687fe03a759470e220452e51"
  },
  {
    "title": "אי עמעום אור הדרך כשלא בנסיעה",
    "symbol": 6687,
    "severity": "*",
    "type": "דמ\"ש",
    "description": "עצרת את הרכב הנ\"ל בזמן תאורה, ולא עמעמת את אור הדרך כשנסעת מאחורי רכב, בניגוד לתקנה 99(א)(2) לתקנות התעבורה",
    "id": "68809eec3eb1adb3683301ee"
  },
  {
    "title": "אי עמעום אור הדרך בנסיעה אחרי רכב",
    "symbol": 6686,
    "severity": "*",
    "type": "דמ\"ש",
    "description": "נהגת ברכב הנ\"ל בזמן תאורה, ולא עמעמת את אור הדרך כשנסעת מאחורי רכב ואלומת אור הדרך של רכבך האירה את חלקו האחורי של הרכב הנוסע לפניך, בניגוד לתקנה 99(א)(3) לתקנות התעבורה",
    "id": "68809fa73eb1adb3683301ef"
  },
  {
    "title": "שימוש באור הדרך, בדרך עירונית מוארת",
    "symbol": 6368,
    "severity": "*",
    "type": "דמ\"ש",
    "description": "נהגת ברכב הנ\"ל בזמן תאורה, בדרך עירונית מוארת כראוי, כשבפנסי החזית דולק אור דרך, בניגוד לתקנה 98 לתקנות התעבורה",
    "id": "6880a02f3eb1adb3683301f0"
  },
  {
    "title": "שימוש בפנס לנסיעה אחורית ללא צורך",
    "symbol": 6685,
    "severity": "*",
    "type": "דמ\"ש",
    "description": "השתמשת בפנס לנסיעה אחורית של הרכב הנ\"ל, שלא בעת נסיעה אחורנית, בניגוד לתקנה 107 (ה) לתקנות התעבורה",
    "id": "6880a0d03eb1adb3683301f1"
  },
  {
    "title": "התקנת פנס נוסף",
    "symbol": 6684,
    "severity": "*",
    "type": "דמ\"ש",
    "description": "התקנת ברכב הנ\"ל פנס נוסף או מתקן מפיץ אור נוסף על הפנסים והאורות, מבלי שקיבלת היתר לכך מרשות הרישוי, בניגוד לתקנה 350 (א) לתקנות התעבורה",
    "note": "הכוונה לפנסים המותקנים מחוץ לרכב, כולל תאורה צבעונית בגחון הרכב. בתוך הרכב מותר להתקין פנסים נוספים",
    "id": "6880a1723eb1adb3683301f2"
  },
  {
    "title": "שימוש בצופר (סירנה) או פנס כחול מהבהב ללא אישור מקמצ\"ר",
    "symbol": 6276,
    "symbol2": 6683,
    "severity": "***",
    "type": "דמ\"ש",
    "description": "בנוהגך ברכב הצבאי הנ\"ל, נהגת בו כאשר עשית שימוש באור כחול מהבהב ו/או מערכת כריזה ללא אישור מתאים לכך, בניגוד לפקודות הצבא",
    "id": "6880a2183eb1adb3683301f3"
  },
  {
    "title": "אי מתן אות לפני תנועת הרכב",
    "symbol": 6280,
    "severity": "*",
    "type": "דמ\"ש",
    "description": "לא אותת בעת שהתכוננת לנוע עם רכבך הנ\"ל, בניגוד לתקנה 58(א)(1) לתקנות התעבורה",
    "id": "6880a2dc3eb1adb3683301f4"
  },
  {
    "title": "פנייה ללא מתן אות שמאלה",
    "symbol": 6280,
    "severity": "*",
    "type": "דמ\"ש",
    "description": "ברכב הנ\"ל ולא אותת בעת שהתכוננת להפנות את רכבך שמאלה, בניגוד לתקנה 58(א)(1) לתקנות התעבורה",
    "id": "6880a31f3eb1adb3683301f5"
  },
  {
    "title": "פנייה ללא מתן אות ימינה",
    "symbol": 6280,
    "severity": "*",
    "type": "דמ\"ש",
    "description": "ברכב הנ\"ל ולא אותת בעת שהתכוננת להפנות את רכבך ימינה, בניגוד לתקנה 58(א)(1) לתקנות התעבורה",
    "id": "6880a36b3eb1adb3683301f6"
  },
  {
    "title": "סטייה מהנתיב ללא מתן אות",
    "symbol": 6280,
    "severity": "*",
    "type": "דמ\"ש",
    "description": "נהגת ברכב הנ\"ל ולא אותת לפני שסטית מנתיב נסיעתך, בניגוד לתקנה 58(א)(2) לתקנות התעבורה",
    "id": "6880a4063eb1adb3683301f7"
  },
  {
    "title": "אי החזקת ההגה של רכב מנועי בשתי ידיים",
    "symbol": 6301,
    "severity": "**",
    "type": "דמ\"ש",
    "description": "נהגת ברכב הנ\"ל, ולא החזקת בשתי ידיך את ההגה, בזמן שהרכב היה בתנועה, וזאת בעת שלא עשית כל פעולה לקיום כללי התנועה או הבטחת הנהיגה, בניגוד לתקנה 28(א) לת\"ת",
    "id": "6880a5363eb1adb3683301f8"
  },
  {
    "title": "אי ציות להוראת שוטר צבאי במדים או שוטר שהזדהה על-ידי תעודת מינוי",
    "symbol": 6370,
    "severity": "***",
    "type": "דמ\"ש",
    "description": "נהגת ברכב הנ\"ל, ולא ציית להוראות שוטר במדים/שוטר שהזדהה על-ידי הצגת תעודת מינוי, שהורה לך...(תאר את פרטי המקרה), בניגוד לתקנה 23(א)(1) בניגוד לתקנות התעבורה",
    "note": "עבירה שמופיעה גם כהולך רגל",
    "id": "6880a5a03eb1adb3683301f9"
  },
  {
    "title": "אי ציות לאות של שוטר במדים",
    "symbol": 6370,
    "severity": "***",
    "type": "דמ\"ש",
    "description": "נהגת ברכב הנ\"ל ולא ציית לאות עצור/התקדם/סע ימינה/סע שמאלה/סע לאחור שנתן לך שוטר במדים, בניגוד לתקנה 23(א)(2) לתקנות התעבורה",
    "note": "עבירה שמופיעה גם כהולך רגל",
    "id": "6880a61d3eb1adb3683301fa"
  },
  {
    "title": "אי לבישת אפוד זוהר ביציאה/ירידה מרכב בדרך בין עירונית",
    "symbol": 6398,
    "severity": "**",
    "type": "דמ\"ש",
    "description": "נהגת ברכב הנ\"ל בדרך בין עירונית, יצאת/ירדת מהרכב, כשאינך לבוש אפוד זוהר בניגוד לסעיף 65 ב' לפקודת התעבורה",
    "note": "אין לערוך דו\"ח אם הייתה קיימת מדרכה והנהג ירד אל המדרכה ושהה עליה, אין לערוך דו\"ח אם אחד מנוסעי הרכב כשהוא לבוש אפודה",
    "id": "6880a6c23eb1adb3683301fb"
  },
  {
    "title": "בלימה בפתאומיות שלא לשם מניעת תאונה",
    "symbol": 6379,
    "severity": "**",
    "type": "דמ\"ש",
    "description": "נהגת ברכב הנ\"ל ובלמת בפתאומיות שלא לשם מניעת תאונה ומבלי שהדבר היה דרוש לבטיחות התנועה, בניגוד לתקנה 53 לתקנות התעבורה",
    "id": "6880a77b3eb1adb3683301fc"
  },
  {
    "title": "גרירת מכונה נגררת ברכב פרטי שמשקלו הכולל אינו עולה על 2,200 ק\"ג",
    "symbol": 6354,
    "severity": "*",
    "type": "דמ\"ש",
    "description": "נהגת ברכב הפרטי הנ\"ל, שמשקלו הכולל אינו עולה על 2,200 ק\"ג, וגררת מכונה נגררת הפטורה מרישום ורישוי, ללא היתר מרשות הרישוי, בניגוד לתקנה 91 (א) לת\"ת",
    "id": "6880bc659f477c79fe7b0f08"
  },
  {
    "title": "גרירת רכב מנועי ברכב פרטי שמשקלו הכולל אינו עולה על 2,200 ק\"ג",
    "symbol": 6354,
    "severity": "*",
    "type": "דמ\"ש",
    "description": "נהגת ברכב הפרטי הנ\"ל, שמשקלו הכולל אינו עולה על 2,200 ק\"ג, וגררת רכב מנועי ללא היתר מרשות הרישוי, ללא היתר מרשות הרישוי, בניגוד לתקנה 91 (ג) לת\"ת",
    "id": "6880bd339f477c79fe7b0f0a"
  },
  {
    "title": "גרירת מכונה נגררת ברכב מסחרי שמשקלו הכולל אינו עולה על 2,200 ק\"ג",
    "symbol": 6354,
    "severity": "*",
    "type": "דמ\"ש",
    "description": "נהגת ברכב הנ\"ל, שמשקלו הכולל אינו עולה על 2,200 ק\"ג, וגררת מכונה נגררת הפטורה מרישום ורישוי, ללא היתר מרשות הרישוי, ללא היתר מרשות הרישוי, בניגוד לתקנה 91 (ג) לת\"ת",
    "id": "6880bd919f477c79fe7b0f0b"
  },
  {
    "title": "גרירת יותר מגרור אחד",
    "symbol": 6678,
    "severity": "*",
    "type": "דמ\"ש",
    "description": "נהגת ברכב הנ\"ל, וגררת יותר מגרור אחד, ללא היתר מרשות הרישוי, בניגוד לתקנה 91 (ג) לתקנות התעבורה",
    "id": "6880bde89f477c79fe7b0f0c"
  },
  {
    "title": "גרירת יותר מרכב אחד",
    "symbol": 6335,
    "severity": "*",
    "type": "דמ\"ש",
    "description": "נהגת ברכב הנ\"ל, וגררת יותר מרכב אחד, ללא היתר מרשות הרישוי, בניגוד לתקנה 91 (ג) לתקנות התעבורה",
    "id": "6880be2b9f477c79fe7b0f0d"
  },
  {
    "title": "גרירה המבוצעת שלא בהתאם לתקנות גרירת רכב שלא באמצעות מוט חיבור",
    "symbol": 6335,
    "severity": "*",
    "type": "דמ\"ש",
    "description": "נהגת ברכב הנ\"ל, וגררת רכב מנועי אחר, מבלי שהיה מחובר במוט חיבור מתאים, בניגוד לתקנה 91 (א) לתקנות התעבורה",
    "id": "6880be689f477c79fe7b0f0e"
  },
  {
    "title": "גרירה המבוצעת שלא בהתאם לתקנות גרירת רכב שלא באמצעות מוט חיבור",
    "symbol": 6336,
    "severity": "*",
    "type": "דמ\"ש",
    "description": "נהגת ברכב הנ\"ל, וגררת רכב מנועי אחר, כשהמרחק בין שני כלי רכב עלה על 2.5 מטר, בניגוד לתקנה 90 (א) לתקנות התעבורה",
    "id": "6880bec69f477c79fe7b0f0f"
  },
  {
    "title": "אי הרמת גלגלי הסרן של הנגרר",
    "symbol": 6337,
    "severity": "*",
    "type": "דמ\"ש",
    "description": "נהגת ברכב הנ\"ל, וגררת רכב מנועי אחר כשגלגלי הסרן שלו, לא היו מורמים ובנגרר לא נהג אדם בעל רישיון נהיגה לסוג הרכב הנגרר, בניגוד לתקנה 91 (ד) לתקנות התעבורה",
    "id": "6880bf239f477c79fe7b0f10"
  },
  {
    "title": "גרירת רכב שלא בבטחה",
    "symbol": 6349,
    "severity": "*",
    "type": "דמ\"ש",
    "description": "נהגת ברכב הנ\"ל, וגררת רכב מנועי אחר, מבלי שהדבר נעשה בבטחה, בניגוד לתקנה 91 (ו) לתקנות התעבורה",
    "id": "6880bf729f477c79fe7b0f11"
  },
  {
    "title": "העדר סימון \"נגרר\" בחלק האחורי",
    "symbol": 6338,
    "severity": "*",
    "type": "דמ\"ש",
    "description": "נהגת ברכב הנ\"ל וגררת רכב מנועי אחר, כשהרכב הנגרר לא סומן מאחור במילה \"נגרר\", בניגיוד לתקנה 91 (ב) לתקנות התעבורה",
    "id": "6880bfbd9f477c79fe7b0f12"
  },
  {
    "title": "נהיגת רכב שעולה ממנו אבק/שנשפך ממנו חומר",
    "symbol": 6677,
    "severity": "**",
    "type": "דמ\"ש",
    "description": "נהגת ברכב הנ\"ל, שעלה ממנו אבק/שנשפך ממנו חומר, בניגוד לתקנה 86(1) לתקנות התעבורה",
    "id": "6881cee00f7330ac417e0b5b"
  },
  {
    "title": "נהיגת רכב שנשמט ממנו מטען",
    "symbol": 6676,
    "severity": "**",
    "type": "דמ\"ש",
    "description": "נהגת ברכב הנ\"ל, שנשמט ממנו מטען, בניגוד לתקנה 85(א)(4) לתקנות התעבורה",
    "id": "6881cf3b0f7330ac417e0b5c"
  },
  {
    "title": "המטען אינו מחוזק היטב",
    "symbol": 6371,
    "severity": "**",
    "type": "דמ\"ש",
    "description": "נהגת ברכב הנ\"ל, והובלת מטען שלא היה מחוזק היטב, בניגוד לתקנה 85(א)(4) לתקנות התעבורה",
    "id": "6881cf9d0f7330ac417e0b5d"
  },
  {
    "title": "מכסה המטען אינו מחוזק היטב",
    "symbol": 6371,
    "severity": "*",
    "type": "דמ\"ש",
    "description": "נהגת ברכב הנ\"ל, והובלת מטען, כשמכסה המטען לא היה מחוזק היטב, בניגוד לתקנה 85(א)(4) לתקנות התעבורה",
    "id": "6881cfe00f7330ac417e0b5e"
  },
  {
    "title": "המטען או מכסהו מגבילים את שדה הראייה של הנהג",
    "symbol": 6316,
    "severity": "*",
    "type": "דמ\"ש",
    "description": "נהגת ברכב הנ\"ל, והובלת ברכב/על רכב מטען שחסם/שמכסהו חסם/שהגביל/שמכסהו הגביל את שדה ראייתך לפנים/מהצד, בניגוד לתקנה 85(א)(4)(ב) לתקנות התעבורה",
    "id": "6881d06b0f7330ac417e0b5f"
  },
  {
    "title": "המטען/מכסה המטען/מסתיר את לוחית הזיהוי הקדמית/האחורית",
    "symbol": 6299,
    "severity": "*",
    "type": "דמ\"ש",
    "description": "נהגת ברכב הנ\"ל, והובלת מטען/מכסה מטען שהסתיר את לוחית הזיהוי הקדמית/האחורית של הרכב מעיני עוברי דרך, בניגוד לתקנה 85(א)(2)(ג) לתקנות התעבורה",
    "id": "6881d0ff0f7330ac417e0b60"
  },
  {
    "title": "מטען/מכסה מטען מסתירים מראות תשקיף (כולל מצבים בהם הרכב בו מובל המטען מלווה ע\"י רכב אחד)",
    "symbol": 6675,
    "severity": "*",
    "type": "דמ\"ש",
    "description": "נהגת ברכב הנ\"ל והובלת ברכב/על הרכב מטען, שהמטען/מכסה המטען הסתיר את מראות התשקיף, בניגוד לתקנה 85(א)(2)(ב) לתקנות התעבורה",
    "id": "6881d2dd0f7330ac417e0b61"
  },
  {
    "title": "הובלת מטען בתפזורת ללא כיסוי מתאים",
    "symbol": 6674,
    "severity": "*",
    "type": "דמ\"ש",
    "description": "נהגת ברכב הנ\"ל, והובלת מטען בתפזורת, שגובהו עלה על דפנות הארגז של הרכב לרבות גובה הסולמות/בלא שהמטען היה מכוסה כיסוי מתאים, בניגוד לתקנה 95(א)(6) לתקנות התעבורה",
    "id": "6881d3640f7330ac417e0b62"
  },
  {
    "title": "הושטת יד לטרמפ",
    "symbol": 8068,
    "severity": "**",
    "type": "דמ\"ש",
    "description": "בהיותך חייל/ת מדי צה\"ל, הושטת ידך בכדי לעצור טרמפ במקום אסור בניגוד לפ\"מ",
    "id": "689236659a33841c451b04d7"
  },
  {
    "title": "הושטת יד תוך עליה לטרמפ",
    "symbol": 8069,
    "severity": "**",
    "type": "דמ\"ש",
    "description": "בהיותך חייל/ת מדי צה\"ל, הושטת ידך ועלית לטרמפ במקום אסור בניגוד לפ\"מ",
    "id": "689236979a33841c451b04d9"
  },
  {
    "title": "עליה לטרמפ במסגרת \"מבצע חטיפות דמה\" (שיפוט אל\"מ)",
    "symbol": 8070,
    "severity": "***",
    "type": "דמ\"ש",
    "description": "בהיותך חייל/ת מדי צה\"ל, הושטת ידך ועלית לטרמפ של מ\"צ במקום אסור בניגוד לפ\"מ",
    "id": "689236ce9a33841c451b04dc"
  },
  {
    "title": "נהיגת רכב כאשר הראות מן השמשות מוגבלת",
    "symbol": 6705,
    "severity": "*",
    "type": "דמ\"ש",
    "note": "דוח זהה נרשם כאשר חפץ מטען או סימון מסתירים שדה או שיש וילון סגור אחורי או מספר מדבקות המכסה מלמעלה לשליש מהשמשה, אין לערוך דו\"ח על הגבלת ראות בשמשה האחורית במקרה של רכב שבו מותקנות מראות תשקיף",
    "description": "נהגת ברכב הנ\"ל, בו הוגבלה יכולתך לראות את הדרך והתנועה בה מן השמשה הקדמית של הרכב/האחורית של הרכב/שלצד הנהג/שלצד הנוסע במושב  הקדמי, בניגוד לתקנה 27(ד) לתקנות התעבורה",
    "id": "689237259a33841c451b04df"
  },
  {
    "title": "קיפוח זכות השימוש בדרך",
    "symbol": 6700,
    "severity": "**",
    "type": "דמ\"ש",
    "description": "בהיותך עובר דרך התנהגת באופן אשר קיפח את זכות אדם להשתמש שימוש מלא בדרך בכך ש... (פרט את מעשה הנהג), בניגוד לתקנה 21(ב)(1) לתקנות התעבורה",
    "id": "68923b8f9a33841c451b04e2"
  },
  {
    "title": "הסעת נוסעים במספר העולה על המצוין ברישיון הרכב",
    "symbol": 6013,
    "severity": "***",
    "type": "דמ\"ש",
    "description": "נהגת ברכב הנ\"ל והסעת בו נוסעים...... במספר העולה על.... נוסעים כמצוין ברישיון הרכב, בניגוד לתקנה 84(ב) לתקנות התעבורה",
    "id": "68923bf49a33841c451b04e3"
  },
  {
    "title": "הליכה בכביש כשיש לצידו מדרכה",
    "symbol": 6734,
    "severity": "**",
    "type": "דמ\"ש",
    "description": "הלכת בכביש, כשהייתה לצידו מדרכה, בניגוד לתקנה 108 (א) לתקנות התעבורה",
    "id": "68923bf49a33841c451b04e4"
  },
  {
    "title": "הליכה בכביש כשיש לצידו שוליים תקינים",
    "symbol": 6735,
    "severity": "**",
    "type": "דמ\"ש",
    "description": "הלכת בכביש, כשהיו לצידו שוליים תקינים, בניגוד לתקנה 108 (א) לתקנות התעבורה ",
    "id": "68923bf49a33841c451b04e5"
  },
  {
    "title": "הליכה בכביש כשיש לצידו שביל הולכי רגל",
    "symbol": 6736,
    "severity": "**",
    "type": "דמ\"ש",
    "description": "הלכת בכביש, כשהיה לצידו שביל להולכי רגל, בניגוד לתקנה 108 (א) לתקנות התעבורה",
    "id": "68923bf49a33841c451b04e6"
  },
  {
    "title": "הליכה בכביש שלא בצד השמאל",
    "symbol": 6737,
    "severity": "*",
    "type": "דמ\"ש",
    "description": "הלכת בכביש, שלא בסמוך לשפתו השמאלית, כשפניך לא אל התנועה הבאה לקראתך, בניגוד לתקנה 109 (א) לתקנות התעבורה",
    "id": "68923bf49a33841c451b04e7"
  },
  {
    "title": "הליכה בכביש שלא בצד השמאל",
    "symbol": 6737,
    "severity": "*",
    "type": "דמ\"ש",
    "description": "הלכת בכביש, שלא בסמוך לשפתו השמאלית, כשפניך לא אל התנועה הבאה לקראתך, בניגוד לתקנה 109 (א) לתקנות התעבורה",
    "id": "68923bf49a33841c451b04e7"
  },
  {
    "title": "חציית כביש כשברמזור אור אדום",
    "symbol": 6254,
    "severity": "**",
    "type": "דמ\"ש",
    "description": "לא ציית לרמזור, בכך שהתחלת לחצות את הכביש כשברמזור המוצב בכיוון חצייתך היה אור אדום, בניגוד לתקנה 22(א) לתקנות התעבורה",
    "id": "68923bf49a33841c451b04e7"
  },
  {
    "title": "חציית כביש שלא במנהרה",
    "symbol": 6260,
    "severity": "**",
    "type": "דמ\"ש",
    "description": "חצית כביש שלא במנהרה להולכי רגל המצויה בקרבת מקום, בניגוד לתקנה 110(ב) לתקנות התעבורה",
    "id": "68923bf49a33841c451b04e8"
  },
  {
    "title": "חציית כביש שלא במעבר חצייה",
    "symbol": 6255,
    "severity": "**",
    "type": "דמ\"ש",
    "description": "חצית כביש שלא במעבר חציה המצוי בקרבת מקום, בניגוד לתקנה 110(ב) לתקנות התעבורה",
    "id": "68923bf49a33841c451b04e9"
  },
  {
    "title": "חציית כביש שלא על גשר להולכי רגל",
    "symbol": 6260,
    "severity": "**",
    "type": "דמ\"ש",
    "description": "חצית כביש, שלא על גשר להולכי רגל המצוי בקרבת מקום, בניגוד לתקנה 110(ב) לתקנות התעבורה",
    "id": "68923bf49a33841c451b04e10"
  },
  {
    "title": "חציית כביש בצורה מסוכנת",
    "symbol": 6258,
    "severity": "**",
    "type": "דמ\"ש",
    "description": "חצית כביש שלא בבטחה, מבלי שבדקת את מצב התנועה ואפשרות החצייה, בניגוד לתקנה 110(ב) לתקנות התעבורה",
    "id": "68923bf49a33841c451b04e11"
  },
  {
    "title": "חציית כביש במקום בו מותקן מעקה בטיחות",
    "symbol": 6738,
    "severity": "**",
    "type": "דמ\"ש",
    "description": "חצית כביש, במקום שבו מותקן מעקה בטיחות בצד הכביש, בניגוד לתקנה 113(א) לתקנות התעבורה",
    "id": "68923bf49a33841c451b04e12"
  },
  {
    "title": "חציית כביש במקום שבו מותקנת גדר בשטח ההפרדה",
    "symbol": 6259,
    "severity": "**",
    "type": "דמ\"ש",
    "description": "חצית כביש, במקום שבו מותקנת גדר בשטח הפרדה שבדרך, בניגוד לתקנה 113(א) לתקנות התעבורה",
    "id": "68923bf49a33841c451b04e13"
  },
  {
    "title": "חציית כביש במקום שבו גדלה צמחייה בשטח ההפרדה",
    "symbol": 6259,
    "severity": "**",
    "type": "דמ\"ש",
    "description": "חצית כביש, במקום שבו גדלה צמחייה בשטח ההפרדה שבדרך, בניגוד לתקנה 113(א) לתקנות התעבורה",
    "id": "68923bf49a33841c451b04e14"
  },
  {
    "title": "ירידה מהמדרכה לכביש, ללא זהירות",
    "symbol": 6739,
    "severity": "**",
    "type": "דמ\"ש",
    "description": "ירדת באופן פתאומי מהמדרכה לכביש, בזמן שהתקרב אליך רכב ולא היה באפשרות הנהג לעוצרו כדי למנוע תאונה, בניגוד לתקנה 111 לתקנות התעבורה",
    "id": "68923bf49a33841c451b04e15"
  },
  {
    "title": "ירידה ממקום מבטחים לכביש, ללא זהירות",
    "symbol": 6740,
    "severity": "**",
    "type": "דמ\"ש",
    "description": "ירדת באופן פתאומי ממקום מבטחים לכביש, בזמן שהתקרב אליך רכב ולא היה באפשרות הנהג לעוצרו כדי למנוע תאונה, בניגוד לתקנה 111 לתקנות התעבורה",
    "id": "68923bf49a33841c451b04e16"
  },
  {
    "title": "הפרעה להולכי רגל על המדרכה",
    "symbol": 6261,
    "severity": "**",
    "type": "דמ\"ש",
    "description": "גרמת להפרעה לתנועת הולכי רגל על המדרכה, בכך *פרט עובדות*, בניגוד לתקנה 114 לתקנות התעבורה",
    "id": "68923bf49a33841c451b04e17"
  },
  {
    "title": "הימצאות בכביש שלא בתוקף תפקיד רשמי",
    "symbol": 6262,
    "severity": "*",
    "type": "דמ\"ש",
    "description": "עמדת בכביש, שלא בתוקף תפקיד רשמי, בניגוד לתקנה 112 לתקנות התעבורה",
    "id": "68923bf49a33841c451b04e18"
  },
  {
    "title": "אי פינוי דרך לרכב ביטחון על ידי הולך רגל",
    "symbol": 6211,
    "severity": "*",
    "type": "דמ\"ש",
    "description": "נמצאת בכביש, בעת שרכב ביטחון התקרב, ולא פינית מיד את הדרך למעבר רכב הביטחון, בניגוד לתקנה 93(א)(2) לתקנות התעבורה",
    "id": "68923bf49a33841c451b04e19"
  },
  {
    "title": "הימצאות למעבר למעקה בטיחות",
    "symbol": 6264,
    "severity": "*",
    "type": "דמ\"ש",
    "description": "נמצאת מעבר למעקה בטיחות, בצד הכביש, בניגוד לתקנה 113(ב) לתקנות התעבורה",
    "id": "68923bf49a33841c451b04e20"
  },
  {
    "title": "אי-ציות לתמרור 413-האוסר על הולך רגל להיכנס לדרך",
    "symbol": 6199,
    "severity": "*",
    "type": "דמ\"ש",
    "description": "לא ציית לתמרור ב-64 בכך שנכנסת לדרך בה מוצב התמרור, בניגוד לתקנה 22(א) לתקנות התעבורה",
    "id": "68923bf49a33841c451b04e21"
  },
  {
    "title": "צעידה של קבוצת אנשים ללא אור (האחראי בזמן הצעידה)",
    "symbol": 6742,
    "severity": "*",
    "type": "דמ\"ש",
    "description": "היית אחראי על קבוצת אנשים, שצעדו בזמן תאורה בכביש בלתי מואר, ולא דאגת שהצועד הראשון והצועד האחרון בקבוצה הקרוב לצד התנועה יישאו אור נייד או מחזיר אור, שנהגי כלי רכב יוכלו להבחין בו ממרחק סביר, בניגוד לתקנה 109(ב) לתקנות התעבורה",
    "id": "68923bf49a33841c451b04e22"
  },
  {
    "title": "חציית מפגש מסילת ברזל על ידי הולך רגל",
    "symbol": 6743,
    "severity": "*",
    "type": "דמ\"ש",
    "description": "חציית מסילת ברזל במפגש, מבלי שבדקת אם אין רכבת מתקרבת, ומבלי שנוכחת לדעת כי אפשר לחצות את המסילה בבטחה, בניגוד לתקנה 117(א) לתקנות התעבורה",
    "id": "68923bf49a33841c451b04e23"
  },
  {
    "title": "חציית מסילת ברזל כשניתן אור אזהרה",
    "symbol": 6744,
    "severity": "**",
    "type": "דמ\"ש",
    "description": "חצית את מסילת הברזל/התקדמת מעבר למחסום/התקדמת מעבר לגדר מסילת הברזל/התקדמת למרחק כשהוא פחות מ-6 מטר לפני פס המסילה הקרוב, כשניתן אות אזהרה על התקרבות הרכבת, בניגוד לתקנה 117(ב) לתקנות התעבורה",
    "id": "68923bf49a33841c451b04e24"
  },
  {
    "title": "חציית מסילת ברזל כשהמחסום נע",
    "symbol": 6745,
    "severity": "**",
    "type": "דמ\"ש",
    "description": "חצית את מסילת הברזל/התקדמת מעבר למחסום/התקדמת מעבר לגדר מסילת הברזל/התקדמת למרחק כשהוא פחות מ-6 מטר לפני פס המסילה הקרוב, כשהמחסום שלפני המפגש התחיל להתנועע לחסימת/פתיחת הדרך, בניגוד לתקנה 117(ב) לתקנות התעבורה",
    "id": "68923bf49a33841c451b04e25"
  },
  {
    "title": "מעבר דרך מחסום של מסילת ברזל",
    "symbol": 6746,
    "severity": "**",
    "type": "דמ\"ש",
    "description": "עברת דרך מחסום/מסביב למחסום/מעל למחסום/מתחת למחסום של מפגש מסילת ברזל, בזמן שהיה סגור/תוך כדי סגירתו, בניגוד לתקנה 117(ג) לתקנות התעבורה",
    "id": "68923bf49a33841c451b04e26"
  },
  {
    "title": "הפרעה וסיכון לתנועה (נסיבות מחמירות)",
    "symbol": 6701,
    "severity": "***",
    "type": "ביד\"צ",
    "description": "גרמת הפרעה וסיכון לתנועה בכך שהחנית את הרכב הנ\"ל על נתיב נסיעה, בניגוד לתקנה 71(1) לתקנות התעבורה",
    "id": "68923bf49a33841c451b04e27",
    "note": "יש לפרט בדו\"ח כיצד בא לידי ביטוי הסיכון שנגרם"
  },
  {
    "title": "הפרעה לתנועה / עיכוב תנועה",
    "symbol": 4867,
    "severity": "**",
    "type": "ביד\"צ",
    "description": "גרמת הפרעה / עיכוב לתנועה כשנהגת ברכב הנ\"ל בכך ש... (פרט עובדות), בניגוד לתקנה 21(ב)(3)",
    "id": "68923bf49a33841c451b04e28"
  },
  {
    "title": "הרכב נמצא במצב העלול לסכן עוברי דרך",
    "symbol": 4867,
    "severity": "**",
    "type": "ביד\"צ",
    "description": "נהגת ברכב הנ\"ל כשהרכב נמצא במצב העלול לסכן עוברי דרך, בניגוד לתקנה 27 (א) לתקנות התעבורה",
    "id": "68923bf49a33841c451b04e29"
  },
  {
    "title": "הפרעה לעוברי דרך בעת כניסה למסלול התנועה",
    "symbol": 6699,
    "severity": "**",
    "type": "ביד\"צ",
    "description": "הסעת את הרכב הנ\"ל, שעמד בצד הכביש, והפרעת לעוברי דרך בשעת הכניסה למסלול התנועה בכך ש... (פרט העובדות), בניגוד לתקנה 66 לתקנות התעבורה",
    "id": "68923bf49a33841c451b04e30"
  },
  {
    "title": "הפרעה לעוברי דרך בעת כניסה למסלול התנועה",
    "symbol": 6386,
    "severity": "**",
    "type": "ביד\"ץ",
    "description": "הסעת את הרכב הנ\"ל, שעמד בצד הכביש, וסיכנת עוברי דרך בעת הכניסה למסלול התנועה בכך ש... (פרט עובדות), בניגוד לתקנה 66 לתקנות התעבורה",
    "id": "68923bf49a33841c451b04e31",
    "note": "יש לפרט בדו\"ח כיצד בא לידי ביטוי הסיכון בנגרם"
  },
  {
    "title": "כניסה לצומת כאשר אין אפשרות להמשיך בנסיעה/כניסה למפגש מסילת ברזל",
    "symbol": 6698,
    "severity": "**",
    "type": "ביד\"ץ",
    "description": "נהגת ברכב הנ\"ל ונכנסת לצומת/מפגש מסילת ברזל, מבלי שהיה ביכולתך לעבור ולהמשיך בנסיעה ללא הפרעה לתנועה, בניגוד לתקנה 56 לתקנות התעבורה",
    "id": "68923bf49a33841c451b04e32"
  },
  {
    "title": "אי פינוי רכב מהכביש על-ידי מערוב בנזק בלבד",
    "symbol": 6701,
    "severity": "**",
    "type": "דמ\"ש",
    "description": "לא פינית את הכביש לתנעוה חופשית, לאחר שהרכב הנ\"ל, שנהגת בו, היה מעורב בתאונה של נזק בלבד ועמידתו במקום עלולה הייתה להפריע לתנועה, בניגוד לתקנה 145(ב) לתקנות התעבורה",
    "id": "68923bf49a33841c451b04e33"
  },
  {
    "title": "הוראת נהיגה ללא רישיון",
    "symbol": 6360,
    "severity": "**",
    "type": "דמ\"ש",
    "description": "הורית נהיגה ברכב הנ\"ל, ללא רישיון הוראה/שלא עפ\"י תנאי הרישיון בניגוד לסעיף 245 לתקנות התעבורה",
    "id": "68923bf49a33841c451b04e34"
  },
  {
    "title": "הוראת נהיגה ללא היתר או שלא בהתאם לתנאי ההיתר",
    "symbol": 6762,
    "severity": "*",
    "type": "דמ\"ש",
    "description": "הדרכת נהיגה ברכב הנ\"ל, ללא היתר הדרכה/שלא בהתאם לתנאי ההיתר מסמכות הרישוי, בניגוד לתקנה 255(א) לתקנות התעבורה",
    "id": "68923bf49a33841c451b04e35"
  },
  {
    "title": "נהיגה עם אוזניות",
    "symbol": 8390,
    "severity": "**",
    "type": "דמ\"ש",
    "description": "נהגת ברכב הנ\"ל, כשלאוזניך צמודות אוזניות המחוברות למכשיר להשמעת צלילים או קולות בניגוד לתקנה 169 לתקנות התעבורה",
    "id": "68923bf49a33841c451b04e36"
  },
  {
    "title": "הליכה בכביש עם אוזניות",
    "symbol": 6428,
    "severity": "**",
    "type": "דמ\"ש",
    "description": "הלכת בכביש כשלאוזניך צמודות אוזניות המחוברות למכשיר להשמעת צלילם או קולות, בניגוד לתקנה 169 לתקנות התעבורה",
    "id": "68923bf49a33841c451b04e37"
  },
  {
    "title": "נוסע ברכב שחלק שגופו אינו בפנים הרכב",
    "symbol": 6365,
    "severity": "**",
    "type": "דמ\"ש",
    "description": "נסעת ברכב הנ\"ל, כשלא כל גופך נמצא בפנים הרכב, בניגוד לתקנה 79 (א) לתקנות התעבורה",
    "id": "68923bf49a33841c451b04e38"
  },
  {
    "title": "הסעה של יותר מנוסע אחד לצד הנהג ללא היתר",
    "symbol": 6659,
    "severity": "***",
    "type": "דמ\"ש",
    "description": "נהגת ברכב הנ\"ל, והסעת לצידך יותר מנוסע אחד, ללא היתר מרשות הרישוי, בניגוד לתקנה 82(א) לתקנות התעבורה",
    "id": "68923bf49a33841c451b04e39"
  },
  {
    "title": "הסעת נוסעים לצד הנהג שלא בהתאם לתנאי ההיתר",
    "symbol": 6658,
    "severity": "***",
    "type": "דמ\"ש",
    "description": "נהגת ברכב הנ\"ל, והסעת לידך נוסעים, שלא בהתאם לתנאי ההיתר מטעם רשות הרישוי, בניגוד לתקנה 82(א) לתקנות התעבורה",
    "id": "68923bf49a33841c451b04e40"
  },
  {
    "title": "אי מתן אפשרות להולכי רגל להשלים מעבר חצייה בבטחה",
    "symbol": 6213,
    "severity": "**",
    "type": "ביד\"ץ",
    "description": "נהגת ברכב הנ\"ל, ובהתקרבך למעבר חציה, לא אפשרת להולכי רגל שחצו במעבר להשלים את החצייה בבטחה, בניגוד לתקנה 67(א) לתקנות התעבורה",
    "id": "68923bf49a33841c451b04e41"
  },
  {
    "title": "אי מתן זכות קדימה להולכי רגל תוך סיכון הולכי רגל (נסיבות מחמירות)",
    "symbol": 6213,
    "severity": "**",
    "type": "ביד\"ץ",
    "description": "נהגת ברכב הנ\"ל, ובהתקרבך למעבר חצייה, לא אפשרת להולכי רגל שחצו במעבר להשלים את חצייה בבטחה, תוך קרבה מסוכנות של רכבך להולך הרגל, בניגוד לתקנה 67(א) לתקנות התעבורה",
    "id": "68923bf49a33841c451b04e41"
  },
  {
    "title": "אי מתן זכות קדימה לרכב בעלייה",
    "symbol": 6702,
    "severity": "*",
    "type": "דמ\"ש",
    "description": "נהגת ברכב הנ\"ל בדרך תלולה, שאיננה רחבה במדיה מספקת למעבר חופשי של שני כלי רכב מכיוונים נגדיים, ולא עצרת את רכבך כדי לתת זכות קדימה לרכב העולה, כאשר הנסיבות חייבו עצירתך, בניגוד לתקנה 46(ב) לתקנות התעבורה",
    "id": "68923bf49a33841c451b04e42"
  },
  {
    "title": "אי מתן זכות קדימה לרכב הבא מימן בצומת שלא הוצב בו תמרור",
    "symbol": 6225,
    "severity": "**",
    "type": "ביד\"ץ",
    "description": "נהגת ברכב הנ\"ל, ופנייתך שמאלה בצומת לא נתת זכות קדימה לכלי רכב שבא מימינך, בניגוד לתקנה 46(א)(1) לתקנות התעבורה",
    "id": "68923bf49a33841c451b04e43",
    "note": "לרכבים שמשתלבים משמאל"
  },
  {
    "title": "אי מתן זכות קדימה בפנייה שמאלה",
    "symbol": 6226,
    "severity": "**",
    "type": "ביד\"ץ",
    "description": "נהגת ברכב הנ\"ל, ובפנייתך שמאלה בצומת לא נתת זכות קדימה לרכב אחר שבא ממולך והיה קרוב לצומת, בניגוד לתקנה 64(א)(2) לתקנות",
    "id": "68923bf49a33841c451b04e44"
  },
  {
    "title": "אי מתן זכות קדימה לרכב בדרך סלולה",
    "symbol": 6227,
    "severity": "**",
    "type": "ביד\"ץ",
    "description": "נהגת ברכב והנ\"ל ויצאת מדרך עפר לדרך סלולה, ולא נתת זכות קדימה לרכב המתקרב בדרך סלולה, בניגוד לתקנה 64(א)(3) לתקנות התעבורה",
    "id": "68923bf49a33841c451b04e45"
  },
  {
    "title": "אי מתן זכות קדימה לרכב שבא ממול כשהנתיב חסום",
    "symbol": 6228,
    "severity": "**",
    "type": "ביד\"ץ",
    "description": "נהגת ברכב הנ\"ל בכביש שנתיב תנועתך בו נחסם, ולא נתת זכות קדימה לרכב שבא ממולך, בניגוד לתקנה 68 לתקנות התעבורה",
    "id": "68923bf49a33841c451b04e46"
  },
  {
    "title": "אי מתן זכות קדימה לרכב ביטחון",
    "symbol": 6211,
    "severity": "**",
    "type": "דמ\"ש",
    "description": "נהגת ברכב הנ\"ל בדרך בא עבר / עמד לעבור רכב ביטחון, ולא נתת לו זכות קדימה, בכך שלא עצרת את רכבך קרוב ככל שאפשר לשפת הכביש הימנית עד שעבר רכב זה, בניגוד לתקנה 93(א)(1) לתקנות התעבורה",
    "id": "68923bf49a33841c451b04e47"
  },
  {
    "title": "אי מתן זכות קדימה להולכי רגל לפני עלייה למדרכה או על שול הדרך (ממקום שאינו דרך)",
    "symbol": 6214,
    "severity": "*",
    "type": "ביד\"ץ",
    "description": "נהגת ברכב הנ\"ל ויצאת מחצרים / מדרך גישה לבית / תחנת דלק / מתחנת שירות / ממקום חנייה לכלי רכב / ממקום אחר שאינו דרך, ובעת שנכנסת לדרך לא האטת ולא נתת זכות קדימה להולכי רגל לפני עליה על המדרכה / שול הדרך, בניגוד לתקנה 64(ב)(1) לתקנות התעבורה",
    "id": "68923bf49a33841c451b04e48"
  },
  {
    "title": "אי מתן זכות קדימה לרכב הנע בכביש ביציאה מחצר",
    "symbol": 6227,
    "severity": "*",
    "type": "ביד\"ץ",
    "description": "נהגת ברכב הנ\"ל ויצאת מחצרים / מדרך גישה לבית / תחנת דלק / מתחנת שירות / ממקום חנייה לכלי רכב / ממקום אחר שאינו דרך, ובעת שנכנסת לדרך לא האטת ולא נתת זכות קדימה לכלי רכב שנסעו בכביש, ומתקרבים באותו כביש, בניגוד לתקנה 64(ב)(2) לתקנות התעבורה",
    "id": "68923bf49a33841c451b04e49"
  },
  {
    "title": "הסעת ילד שטרם מלאו לו שלוש שנים במושב הקדמי (למעט אוטובוס מונית ואופנוע) שלא במושב בטיחות",
    "symbol": 6731,
    "severity": "***",
    "type": "דמ\"ש",
    "description": "נהגת ברכב הנ\"ל והסעת במושב הקדמי ילד שטרם מלאו לו שלוש שנים, כשהילד אינו רתום במושב בטיחות המתאים לגובהו ומשקלו, בניגוד לתקנה 83א(ב)(1) לתקנות התעבורה",
    "id": "68923bf49a33841c451b04e50"
  },
  {
    "title": "נהג המסיע נוסע במושב הקדמי לא חגור",
    "symbol": 6004,
    "severity": "***",
    "type": "ביד\"ץ",
    "description": "נהגת ברכב הנ\"ל שהיו מותקנות בו חגורות בטיחות, והנחת לנוסע לשבת במושב הקדמי של הרכב, מבלי שהיה חגור בחגורת בטיחות, בניגוד לתקנה 83ב(א) לתקנות התעבורה",
    "id": "68923bf49a33841c451b04e51"
  },
  {
    "title": "הסעת ילד שטרם מלאה לו שנה במושב הקדמי (למעט אוטובוס מונית ואופנוע). כשגבו של מושב הבטיחות אינן מופנה לחזית הרכב",
    "symbol": 6730,
    "severity": "***",
    "type": "ביד\"ץ",
    "description": "נהגת ברכב הנ\"ל והסעת במושב הקדמי ילד שטרם מלאה לו שנה, כשגבו של מושב הבטיחות בו ישב הילד אינו מופנה לחזית הרכב, בניגוד לתקנה 83א(ג) לתקנות התעבורה",
    "id": "68923bf49a33841c451b04e52"
  },
  {
    "title": "הסעת ילד שטרם מלאה לו שנה במושב האחורי (ברכב ששנת יצורו 1983 ואילך למעט אוטובוס מונית ואופנוע), כשגבו של מושב הבטיחות אינן מופנה לחזית הרכב",
    "symbol": 6730,
    "severity": "***",
    "type": "ביד\"ץ",
    "description": "נהגת ברכב הנ\"ל ששנת יצורו ... והסעת במושב האחורי ילד שטרם מלאה לו שנה, כשגבו של מושב הבטיחות בו ילד הילד אינו מופנה לחזית הרכב, בניגוד לתקנה 83א(ג) לתקנות התעבורה",
    "id": "68923bf49a33841c451b04e53"
  },
  {
    "title": "הסעת ילד שטרם מלאו לו שלוש שנים במושב אחורי (ברכב ששנת יצורו ואילך, למעט אוטובוס מונית ואופנוע), שלא במושב בטיחות",
    "symbol": 6002,
    "severity": "***",
    "type": "ביד\"ץ",
    "description": "נהגת ברכב הנ\"ל ששנת יצורו... והסעת במושב האחורי ילד שטרם מלאו לו שלוש שנים, כשהילד אינו רתום במושב בטיחות המתאים לגרבהו ומשקלו, בניגוד לתקנה 83א(ב)(1) לתקנות התעבורה",
    "id": "68923bf49a33841c451b04e54"
  },
  {
    "title": "הסעת ילד שמלאו לו שלוש שנים אך לא מלאו לו שמונה שנים במושב הקדמי (למעט אוטובוס מונית ואופנוע) כשהילד אינו רתום במושב בטיחות או מושב מגביה",
    "symbol": 6731,
    "severity": "***",
    "type": "ביד\"ץ",
    "description": "נהגת ברכב הנ\"ל והסעת במושב הקדמי ילד שטרם מלאו לו שמונה שנים, כשהילד אינו רתום במושב בטיחות או מושב מגביה, המתאים לגובהו ומשקלו של הילד, בניגוד לתקנה 83א(ב)(2) לתקנות התעבורה ",
    "id": "68923bf49a33841c451b04e55"
  },
  {
    "title": "הסעת ילד שמלאו לו שלוש שנים אך לא מלאו לו שמונה שנים במושב האחורי ( רכב ששנת יצור 1983 ואילך, למעט אוטובוס מונית ואופנוע) כשהילד אינו רתום במושב בטיחות או מושב מגביה",
    "symbol": 6732,
    "severity": "***",
    "type": "ביד\"ץ",
    "description": "נהגת ברכב הנ\"ל ששנת ייצורו ... והסעת במושב האחורי ילד שטרם מלאו לו שמונה שנים, כשהילד אינו רתום במושב בטיחות או מושב מגביה, המתאים לגובהו ומשקלו של הילד, בניגוד לתקנה 38א(ב)(2) לתקנות התעבורה ",
    "id": "68923bf49a33841c451b04e56"
  },
  {
    "title": "הסעת ילד (למעט אוטובוס מונית ואופנוע), במושב בטיחות במקום יש מולו כרית אויר שלא נותק מנגנון הפעלתה",
    "symbol": 6733,
    "severity": "**",
    "type": "ביד\"ץ",
    "description": "נהגת ברכב הנ\"ל והסעת בן ילד במושב בטיחות, במקום שיש מולו כרית אויר שלא נותק מנגנון הפעלתה, בניגוד לתקנה 83א(ד) לתקנות התעבורה",
    "id": "68923bf49a33841c451b04e57"
  },
  {
    "title": "אי ציות לתמרור 432 - האוסר חנייה",
    "symbol": 6509,
    "severity": "**",
    "type": "דמ\"ש",
    "description": "לא ציית לתמרור 432, בכך שהחנית את הרכב הנ\"ל בדרך, בצד שבו מוצב התמרור הנ\"ל, בניגוד לתקנה 22(א) לתקנות התעבורה",
    "id": "68923bf49a33841c451b04e58"
  },
  {
    "title": "אי ציות לתמרור 433 - האוסר עצירה",
    "symbol": 6412,
    "severity": "**",
    "type": "דמ\"ש",
    "description": "לא ציית לתמרור 433, בכך שעצרת את הרכב הנ\"ל בדרך, בצד שבו מוצב התמרור הנ\"ל, בניגוד לתקנה 22(א) לתקנות התעבורה",
    "id": "68923bf49a33841c451b04e59"
  },
  {
    "title": "אי ציות לתמרור 435 - האוסר חנייה",
    "symbol": 6747,
    "severity": "**",
    "type": "דמ\"ש",
    "description": "לא ציית לתמרור 435, בכך שהחנית את הרכב הנ\"ל, שמשקלו הכולל המותר עולה על 10,000 ק\"ג באזור שבכניסה אליו מוצב תמרור. בניגוד תקנה 22(א) לתקנות התעבורה",
    "id": "68923bf49a33841c451b04e60"
  },
  {
    "title": "אי ציות לתמרור 507 - האוסר עצירה בתחנת מוניות לרכב שאינו מונית, שלא לשם הורדת נוסעים",
    "symbol": 6088,
    "severity": "**",
    "type": "דמ\"ש",
    "description": "לא ציית לתמרור 507 בכך שעצרת את הרכב הנ\"ל בתחום תחנת מוניות,שלא לשם הורדת נוסעים, בניגוד לתקנה 72(א)(14) לתקנות התעבורה",
    "id": "68923bf49a33841c451b04e61"
  },
  {
    "title": "העמדה (כולל חנייה) במקום המיועד לנכה",
    "symbol": 6204,
    "severity": "***",
    "type": "דמ\"ש",
    "description": "העמדת את הרכב הנ\"ל, ליד תמרור 437 המסמן מקום חניה לרכב של נכה, בניגוד 72(א)(16) לתקנות התעבורה",
    "id": "68923bf49a33841c451b04e62"
  },
  {
    "title": "אי ציות לתמרור 815 - האוסר חנייה באי תנועה המסומן על פני הדרך",
    "symbol": 6531,
    "severity": "**",
    "type": "דמ\"ש",
    "description": "לא ציית לתמרור 815 בכך שהחנית את הרכב הנ\"ל באי תנועה המסומן על פני הדרך, בניגוד לתקנה 22 (א) לתקנות התעבורה",
    "id": "68923bf49a33841c451b04e63",
    "note": "עבירה זו מתייחסת לחניית רכב על תחום אי תנועה ולא בעת עקיפה"
  },
  {
    "title": "אי ציות לתמרור 818 - האוסר עצירה לאורך אבני שפה צבועות אדום-לבן",
    "symbol": 6748,
    "severity": "**",
    "type": "דמ\"ש",
    "description": "לא ציית לתמרור 818 בכך שעצרת את הרכב הנ\"ל לאורז קטע של אבני שפה הצבועות אדום-לבן, בניגוד לתקנה 22(א) לתקנות התעבורה",
    "id": "68923bf49a33841c451b04e64"
  },
  {
    "title": "אי ציות לתמרור 511 - אוסר עצירה לאורך אבני שפה צבועות אדום צהוב",
    "symbol": 6749,
    "severity": "**",
    "type": "דמ\"ש",
    "description": "לא ציית לתמרור 511 בכך שעצרת את הרכב הנ\"ל לאורך קטע של אבני שפה הצבועות אדום צהוב, בניגוד לתקנה 22(א) לתקנות התעבורה",
    "id": "68923bf49a33841c451b04e65"
  },
  {
    "title": "אי ציות לתמרור 820 - האוסר חנייה בתוך שטח המסומן על פני הכביש",
    "symbol": 6750,
    "severity": "**",
    "type": "דמ\"ש",
    "description": "לא ציית לתמרור 820 בכך שהחנית את הרכב הנ\"ל בתוך שטח המסומן על פני הכביש, בניגוד לתקנה 22(א) לתקנות התעבורה",
    "id": "68923bf49a33841c451b04e66"
  },
  {
    "title": "אי ציות לתמרור 513 - המתיר עצירה לרכב מסוג מסוים בלבד",
    "symbol": 6104,
    "severity": "**",
    "type": "ביד\"ץ",
    "description": "לא ציית לתמרור 513 בכך שעצרת את הרכב הנ\"ל בשטח המסומן על פני הכביש והמיועד לעצירת כלי רכב מסוג מסוים בלבד, בניגוד לתקנה 22(א) לתקנות התעבורה",
    "id": "68923bf49a33841c451b04e67"
  },
  {
    "title": "אי ציות לתמרור 512 - המתיר עצירה במפרץ לרכב מסוג מסוים בלבד",
    "symbol": 6751,
    "severity": "**",
    "type": "ביד\"ץ",
    "description": "לא ציית לתמרור 512 בכך שעצרת את הרכב הנ\"ל בתוך מפרץ מסומן, המיועד לעצירת כלי רכב מסוג מסוים בלבד, בניגוד לתקנה 22(א) לתקנות התעבורה",
    "id": "68923bf49a33841c451b04e68"
  },
  {
    "title": "אי ציות לתמרור 512 -כאשר הרכב נעצר ליד קו קטעים",
    "symbol": 6751,
    "severity": "**",
    "type": "דמ\"ש",
    "description": "לא ציית לתמרור 512 בכך שעצרת את הרכב הנ\"ל ליד קו קטעים שבצד מפרץ מסומן, בניגוד לתקנה 22(א) לתקנות התעבורה",
    "id": "68923bf49a33841c451b04e69"
  },
  {
    "title": "עצירה (כולל העמדה וחנייה) בתחום של תחנת אוטובוס, המסומן על הכביש",
    "symbol": 6087,
    "severity": "*",
    "type": "דמ\"ש",
    "description": "עצרת את הרכב הנ\"ל, בתחום של תחנת אוטובוס, המסומן על פני הכביש, בניגוד לתקנה 72(א)(12) לתקנות התעבורה",
    "id": "68923bf49a33841c451b04e6a"
  },
  {
    "title": "אי ציות לתמרור 803 בהעמדת רכב סמוך לקו הפרדה רצוף",
    "symbol": 6102,
    "severity": "***",
    "type": "דמ\"ש",
    "description": "לא ציית לתמרור 803 בכך שעצרת את הרכב הנ\"ל ליד קו הפרדה רצוף המסומן בכביש, שלא לשם מילוי הוראות כל דין, בניגוד לתקנה 2(א) לתקנות התעבורה",
    "id": "68923bf49a33841c451b04e6b"
  },
  {
    "title": "עצירה (כולל העמדה וחנייה) לפני תמרור של תחנת אוטובוס",
    "symbol": 6086,
    "severity": "*",
    "type": "דמ\"ש",
    "description": "עצרת את הרכב הנ\"ל, בתחום של 20 מטר לפני תמרור תחנת אוטובוס בניגוד לתקנה 72(א)(12) לתקנות התעבורה",
    "id": "68923bf49a33841c451b04e6c"
  },
  {
    "title": "עצירה (כולל העמדה וחנייה) אחרי תמרור של תחנת אוטובוס",
    "symbol": 6086,
    "severity": "*",
    "type": "דמ\"ש",
    "description": "עצרת את הרכב הנ\"ל, בתחום של 20 מטר אחרי תמרור תחנת אוטובוס, בניגוד לתקנה 72(א)(12) לתקנות התעבורה",
    "id": "68923bf49a33841c451b04e6d"
  },
  {
    "title": "העמדת רכב (כולל חנייה) מול תחום מסומן של תחנת אוטובוס (כשרוחב הכביש פחות מ-12 מטר)",
    "symbol": 6752,
    "severity": "**",
    "type": "דמ\"ש",
    "description": "העמדת את הרכב הנ\"ל בכביש שרוחבו פחות מ-12 מטר, מול תחום של תחנת אוטובוס המסומן על פני הכביש, בניגוד לתקנה 72ל, בניגוד לתקנ(א)(12) לתקנות התעבורה",
    "id": "68923bf49a33841c451b04e6e"
  },
  {
    "title": "העמדת רכב (כולל חנייה) מול תמרור של תחנת אוטובוס, בשטח שלפני/אחרי התמרור (בכביש שרוחבו פחות מ-12 מטר)",
    "symbol": 6753,
    "severity": "*",
    "type": "דמ\"ש",
    "description": "העמדת את הרכב הנ\"ל, בכביש שרוחבו פחות מ-12 מטר, מול תמרור של תחנת אוטובוס ובתחום של 20 מטר לפני/אחרי התמרור, בניגוד לתקנה 72(א)(12) לתקנות התעבורה",
    "id": "68923bf49a33841c451b04e6f"
  },
  {
    "title": "תניה בתחום של 2 מטר מברז כיבוי המסומן על המדרכה/על שולי הכביש",
    "symbol": 6103,
    "severity": "*",
    "type": "דמ\"ש",
    "description": "החנית את הרכב הנ\"ל בתחום של 2 מטר מברז כיבוי, המסומן על המדרכה או על שולי הכביש, בניגוד לתקנה 72(א)(5) לתקנות התעבורה",
    "id": "68923bf49a33841c451b04e70"
  },
  {
    "title": "עצירה (כולל העמדה וחנייה) על גשר",
    "symbol": 6101,
    "severity": "**",
    "type": "דמ\"ש",
    "description": "עצרת את הרכב הנ\"ל על גבי גשר, בניגוד לתקנה 72(א)(11) לתקנות התעבורה",
    "id": "68923bf49a33841c451b04e71"
  },
  {
    "title": "תניה באופן המסתיר תמרור/חלק מתמרור",
    "symbol": 6754,
    "severity": "*",
    "type": "דמ\"ש",
    "description": "החנית את הרכב הנ\"ל באופן שהסתיר תמרור/חלק מתמרור מעיני עוברי דרך, בניגוד לתקנה 71(2) לתקנות התעבורה",
    "id": "68923bf49a33841c451b04e72"
  },
  {
    "title": "עצירה (כולל העמדה וחנייה) המפריעה לתנועה",
    "symbol": 6100,
    "severity": "**",
    "type": "דמ\"ש",
    "description": "עצרת את הרכב הנ\"ל באופן שיש בו משום הפרעה לתנועה, בניגוד לתקנה 71(1) לתקנות התעבורה",
    "id": "68923bf49a33841c451b04e73"
  },
  {
    "title": "עצירה על שול הדרך, בדרך שאינה עירונית",
    "symbol": 6092,
    "severity": "***",
    "type": "דמ\"ש",
    "description": "עצרת את הרכב הנ\"ל בשול הדרך, בדרך שאיננה דרך עירונית, בניגוד לתקנה 69(א) לתקנות התעבורה",
    "id": "68923bf49a33841c451b04e74"
  },
  {
    "title": "עצירת רכב בין גדרות כביש מהיר",
    "symbol": 6093,
    "severity": "***",
    "type": "דמ\"ש",
    "description": "עצרת את הרכב הנ\"ל בין גדרות הקובעות את גבולות רצועת הדרך, מבלי שהדבר הותר בסימן מיוחד, בניגוד לתקנה 69(ג) לתקנות התעבורה",
    "id": "68923bf49a33841c451b04e75"
  },
  {
    "title": "חניה בכניסה לשטח המיועד לכלי רכב (שלא לצורך העלאת נוסעים והורדתם)",
    "symbol": 6104,
    "severity": "**",
    "type": "דמ\"ש",
    "description": "החנית את הרכ הנ\"ל, בכניסה לשטח המיועד לכלי רכב, שלא לצורך העלאת נוסעים או להורדתם, בניגוד לתקנה 72(א)(4) לתקנות התעבורה",
    "id": "68923bf49a33841c451b04e76"
  },
  {
    "title": "עצירה (כולל העמדה וחניה) במעבר חציה",
    "symbol": 6097,
    "severity": "***",
    "type": "דמ\"ש",
    "description": "עצרת את הרכב הנ\"ל בתוך מעבר חציה, בניגוד לתקנה 72(א)(4) לתקנות התעבורה",
    "id": "68923bf49a33841c451b04e77"
  },
  {
    "title": "חניה לפני מעבר חציה (בתחום של 12 מטר)",
    "symbol": 6098,
    "severity": "***",
    "type": "דמ\"ש",
    "description": "החנית את הרכב הנ\"ל בתחום של 12 מטר לפני מעבר חציה, בניגוד לתקנה 72(א)(6) לתקנות התעבורה",
    "id": "68923bf49a33841c451b04e78"
  },
  {
    "title": "העמדת רכב (כולל חניה) סמוך לקו העצירה שלפני צומת או מעבר חציה (בתחום של 12 מטר)",
    "symbol": 6099,
    "severity": "***",
    "type": "דמ\"ש",
    "description": "העמדת את הרכב הנ\"ל בתחום של 12 מטר לפני קו העצירה, בניגוד לתקנה 72(א)(7) לתקנות התעבורה",
    "id": "68923bf49a33841c451b04e79"
  },
  {
    "title": "העמדה (כולל חניה) של רכב שרוחבו עולה על 2.5 מטר",
    "symbol": 6113,
    "severity": "*",
    "type": "דמ\"ש",
    "description": "העמדת בדרך את הרכב הנ\"ל, שרוחבו עולה על 2.5 מטר, בניגוד לתקנה 69(ו)(1) לתקנות התעבורה",
    "id": "68923bf49a33841c451b04e80"
  },
  {
    "title": "עצירה (כולל העמדה וחניה) לצד רכב אחר חונה",
    "symbol": 6105,
    "severity": "*",
    "type": "דמ\"ש",
    "description": "עצרת את הרכב הנ\"ל לצד רכב אחר שעמד לצד הדרך,בניגוד לתקנה 72(א)(10) לתקנות התעבורה",
    "id": "68923bf49a33841c451b04e81"
  },
  {
    "title": "החניית רכב בצורה לא בטוחה",
    "symbol": 6761,
    "severity": "**",
    "type": "דמ\"ש",
    "description": "החנית את הרכב הנ\"ל, מבלי שקטת אמצעי זהירות, הדרושים כדי להבטיח שהרכב לא יזוז בהעדר הנהג, וכתוצאה מכך ... (פרט עובדות), בניגוד לתקנה 74(א) לתקנות התעבורה",
    "id": "68923bf49a33841c451b04e82"
  },
  {
    "title": "החניית רכב כשהמנוע פועל",
    "symbol": 6107,
    "severity": "*",
    "type": "דמ\"ש",
    "description": "החנית את הרכב הניה ללא השגחה, מבלי שהפסקת את פעולת המנוע ומנגנון ההדלקה/שהוצאת את מפתח ההצתה, בניגוד לתקנה 74 (ב) לתקנות התעבורה",
    "id": "68923bf49a33841c451b04e83"
  },
  {
    "title": "החניית רכב בצורה לא בטוחה, בדרך שיש בה שיפוע",
    "symbol": 6110,
    "severity": "**",
    "type": "דמ\"ש",
    "description": "החנית את הרכב הנ\"ל בדרך שיש בה שיפוע, מבלי שבלמת את גלגלי המכונית כראוי, ומבלי שהטית את הגלגלים הקדמיים לעבר אבני השפה, בניגוד לתקנה 74(ג) לתקנות התעבורה",
    "id": "68923bf49a33841c451b04e84"
  },
  {
    "title": "החניית רכב שמשקלו הכולל עולה על 5,000 ק\"ג בדרך שיש בה שיפוע, מבלי להציב נעלי ביטחון (למעט אוטובוס)",
    "symbol": 6110,
    "severity": "**",
    "type": "דמ\"ש",
    "description": "החנית את הרכב הנ\"ל שמשקלו הכולל המותר עולה על 5,000 ק\"ג בדרך שיש בה שיפוע, ולא הצבת מתחת לגלגלים האחוריים נעלי ביטחון, בניגוד לתקנה 74(ד) לתקנות התעבורה",
    "id": "68923bf49a33841c451b04e85"
  },
  {
    "title": "חפץ הנשרך מהרכב (חבל/חוט ברזל/וכדו')",
    "symbol": 6726,
    "severity": "*",
    "type": "דמ\"ש",
    "description": "נהגת ברכב הנ\"ל, כשחפץ נשרך ממנו על הדרך ונוגע בה, בניגוד לתקנה 156 לתקנות התעבורה",
    "id": "68923bf49a33841c451b04e86"
  },
  {
    "title": "השלכת חפץ/פסולת מתוך הרכב",
    "symbol": 6727,
    "symbol2": 6414,
    "severity": "**",
    "type": "דמ\"ש",
    "description": "השלכת חפץ/פסולת מתוך רכב נהגת/נסעת ברכב הנ\"ל, והשלכת מתוכן חפץ/פסולת,בניגוד לתקנה 161 (ב) לתקנות התעבורה",
    "id": "68923bf49a33841c451b04e87"
  },
  {
    "title": "מורה לנהיגה שימוש בטלפון",
    "symbol": 6729,
    "severity": "***",
    "type": "ביד\"ץ",
    "description": "הורית נהיגה ברכב הנ\"ל ובשעת הוראת הנהיגה דיברת בטלפון נייד או קבוע ללא דיבורית - בניגוד לסעיף 16(ב) לפקודת התעבורה",
    "id": "68923bf49a33841c451b04e87"
  },
  {
    "title": "נהיגה בכיוון ההפוך בכביש חד-סטרי",
    "symbol": 6401,
    "severity": "***",
    "type": "דמ\"ש",
    "description": "נהגת ברכב הנ\"ל בכביש חד-סטרי, בכיוון הפוך לכיוון התנועה בניגוד לתקנה 37 לתקנות התעבורה",
    "id": "68923bf49a33841c451b04e88"
  },
  {
    "title": "נהיגה שלא בכיוון החץ",
    "symbol": 8336,
    "severity": "**",
    "type": "דמ\"ש",
    "description": "נהגת ברכב הנ\"ל בכביש המחולק לנתיבים שבהם סומנו חיצים המובילים לצומת, ועברת בצומת / יצאת מהצומת שלא בכיוון החץ ומן בנתיב ממנו נכנסת לצומת, בניגוד לתקנה 36(ד) לתקנות התעבורה",
    "id": "68923bf49a33841c451b04e89"
  },
  {
    "title": "שימוש בכביש/שביל/נתיב מיועד לרכב אחר",
    "symbol": 8345,
    "severity": "**",
    "type": "דמ\"ש",
    "description": "נהגת ברכב הנ\"ל והשתמשת בכביש/שביל/נתיב המיועד והמסומן לסוג רכב אחר מסוג הרכב שבו נהגת, בניגוד לתקנה 34 לתקנות התעבורה",
    "id": "68923bf49a33841c451b04e90"
  },
  {
    "title": "נהיגה בנתיב מרכזי בכביש דו-סטרי (שלא לצורך עקיפה או פניה שמאלה)",
    "symbol": 8338,
    "severity": "*",
    "type": "דמ\"ש",
    "description": "נהגת ברכב הנ\"ל בנתיב מרכזי של כביש דו-סטרי המחולק לשלושה נתיבים שלא לצורך עקיפת רכב אחר או פניה שמאלה, בניגוד לתקנה 40 (ב) לתקנות התעבורה",
    "id": "68923bf49a33841c451b04e91"
  },
  {
    "title": "כניסה לצומת שלא מהנתיב הימני ביותר ברכב מסחרי מעל 10,000 ק\"ג",
    "symbol": 6697,
    "severity": "*",
    "type": "דמ\"ש",
    "description": "נהגת ברכב מסחרי הנ\"ל, שמשקלו הכולל המותר עולה על 10,000 ק\"ג, בכביש שיש בו שני  נתיבים או יותר באותן כיןןן נסיעה, ונכנסת לצומת ועברת בו שלא מהנתיב הימיני ביותר, בניגוד לתקנה 36(ה) לתקנות התעבורה",
    "id": "68923bf49a33841c451b04e91"
  },
  {
    "title": "שימוש בנתיב משמאל לנתיב המרכזי בכביש דו-סטרי בן שלושה נתיבים",
    "symbol": 6703,
    "severity": "*",
    "type": "דמ\"ש",
    "description": "נהגת ברכב הנ\"ל ועברת לנתיב הנמצא משמאל לנתיב המרכזי, בכביש דו-סטרי המחולק לשלושה נתיבים, בניגוד לתקנה 40 (ג) לתקנות התעבורה",
    "note": "יש לציין מה היה הסימון ולאיזה כיוון נסיעה.",
    "id": "1"
  },
  {
    "title": "שימוש בדרך שלא בהתאם למתקנים שהוצבו בדרך",
    "symbol": 6696,
    "severity": "*",
    "type": "דמ\"ש",
    "description": "השתמשת בדרך, שלא בהתאם למתקנים שהוצבו בה בניגוד לתקנה 33 (ב) לתקנות התעבורה.",
    "id": "2"
  },
  {
    "title": "נהיגה משמאל לקו הפרדה רצוף בדרך",
    "symbol": 6234,
    "severity": "***",
    "type": "ביד\"ץ + התלייה",
    "description": "נהגת ברכב הנ\"ל בדרך ועברת/ נהגת משמאל לקו הפרדה רצוף המסומן על פני הכביש, כאשר בצידו הימני לא נמצא קו מקוטע, בניגוד לתקנה 36 (ג) לתקנות התעבורה.",
    "id": "3"
  },
  {
    "title": "נהיגה שלא בכביש",
    "symbol": 6232,
    "severity": "***",
    "type": "ביד\"ץ",
    "description": "נהגת ברכב הנ\"ל ונסעת על השול הימני/שמאלי ולא על הכביש עם ארבעת גלגלי הרכב, בניגוד לתקנה 33 (א) לתקנות התעבורה.",
    "id": "4"
  },
  {
    "title": "עיכוב התנועה ואי ירידה לשול המיוצב",
    "symbol": 6704,
    "severity": "*",
    "type": "ביד\"ץ",
    "description": "נהגת ברכב הנ\"ל, ובשל מטען ברכב/שיפוע הדרך, נאלצת לנסוע במהירות נמוכה שעיכבה את כלי הרכב שנסעו מאחורייך, ולא הימנת לנסוע בשול הדרך, כאשר השול המיוצב באספלט ופני, כדי לאפשר לכלי הרכב מאחורייך לעקםך, בניגוד לתקנה 48 (ג) לתקנות התעבורה.",
    "id": "5"
  },
  {
    "title": "אי התקנת לוחית קדמית/ אחורית",
    "symbol": 6229,
    "severity": "**",
    "type": "דמ\"ש",
    "description": "נהגת ברכב הנ\"ל הרשום בישראל, כשאין הוא נושא עליו לוחית זיהוי קדמית/אחורית, בניגוד לתקנה 165 (ב) לתקנות.",
    "id": "6"
  },
  {
    "title": "אי התקנת לוחית זיהוי בגרור",
    "symbol": 6340,
    "severity": "**",
    "type": "דמ\"ש",
    "description": "נהגת ברכב הנ\"ל, כשמחובר אליו גרור, מבלי שהגרור נשא עליו לוחית זיהוי, בניגוד לתקנה 165 (ב) לתקנות התעבורה.",
    "id": "7"
  },
  {
    "title": "עצירה (כולל העמדה וחניה) בצד מעקה בטיחות ",
    "symbol": 6755,
    "severity": "*",
    "type": "דמ\"ש",
    "description": "עצרת את הרכב הנ\"ל בצד מעקה בטיחות להולכי רגל שבשפת הכביש, בניגוד לתקנה 72(א)(13) לתקנות התעבורה",
    "id": "8"
  },
  {
    "title": "עצירה (כולל העמדה וחנייה) בתוך צומת",
    "symbol": 6096,
    "severity": "**",
    "type": "דמ\"ש",
    "description": "עצרת את הרכב הנ\"ל בתוך צומת, בניגוד לתקנה 72(א)(3) לתקנות התעבורה",
    "id": "9"
  },
  {
    "title": "חניה בתחום 12 מטר מצומת",
    "symbol": 6095,
    "severity": "**",
    "type": "דמ\"ש",
    "description": "החנית את הרכב הנ\"ל בתחום 12 מטר מצומת, בניגוד לתקנה 72(א)(3) לתקנות התעבורה",
    "id": "10"
  },
  {
    "title": "עצירה (כולל העמדה וחניה) בכביש ליד קו הפרדה בלתי מרוסק",
    "symbol": 6102,
    "severity": "**",
    "type": "דמ\"ש",
    "description": "עצרת את הרכב הנ\"ל בכביש שבו קיים. בכיוון הנסיעה נתיב אחד בלבד, המסומן בקו הפרדה בלתי מרוסק, בניגוד לתקנה 72(א)(9) לתקנות התעבורה",
    "id": "11"
  },
  {
    "title": "תיקון רכב בדרך במקום חניה ציבורי",
    "symbol": 6758,
    "severity": "*",
    "type": "דמ\"ש",
    "description": "תיקנת את הרכב הנ\"ל, בדרך/במקום חניה ציבורי, וגרמות בכך מטרד לעוברי דרך, בניגוד לתקנה 154 (א) לתקנות התעבורה",
    "id": "12"
  },
  {
    "title": "השארת רכב מקולקל לזמן העולה על 24 שעות",
    "symbol": 6757,
    "severity": "*",
    "type": "דמ\"ש",
    "description": "השארת את הרכב הנ\"ל, עקב קלקול, בדרך/במקום חניה ציבורי, לזמן העולה על 24 שעות, בניגוד לתקנה 154 (ב) לתקנות התעבורה",
    "id": "13"
  },
  {
    "title": "העמדת רכב על המדרכה עם 2 גלגלים או יותר, ולא נותר מעבר של 1.30 מטר",
    "symbol": 6756,
    "severity": "*",
    "type": "דמ\"ש",
    "description": "העמדת את הרכב הנ\"ל על המדרכה, כמקום שלא הוסדר רכב והחנייתו, בניגוד לתקנה 72(א)(2א) לתקנות התעבורה ",
    "id": "14"
  },
  {
    "title": "עצירה (כולל העמדה וחניה) בתחום 20 מטר לפני ואחרי מפגש מסילת ברזל",
    "symbol": 6106,
    "severity": "**",
    "type": "דמ\"ש",
    "description": "עצרת את הרכב הנ\"ל, בתחום של 20 מטר מהפס הקרוב ביותר של מפגש מסילת ברזל, בניגוד לתקנה 72 (א)( 8) לתקנות התעבורה",
    "id": "15"
  },
  {
    "title": "העמדת רכב על המדרכה בשני גלגלים ונותר מעבר של 1.30 מטר במדרכה",
    "symbol": 6756,
    "severity": "**",
    "type": "דמ\"ש",
    "description": "העמדת את הרכב הנ\"ל המדרכה, במקום שלא הוסדר העמדת רכב והחנייתו. בניגוד לתקנה 72(א)(2א) לתקנות התעבורה",
    "id": "16"
  },
  {
    "title": "עצירה (כולל העמדה וחניה) בצד שמאל של דרך דו סטרית או דרך המחולקת על ידי שטח הפרדה",
    "symbol": 6759,
    "severity": "**",
    "type": "דמ\"ש",
    "description": "עצרת את הרכב הנ\"ל בצד שמאל של דרך שהינה דו סטרית, בניגוד לתקנה 72(א)(1) לתקנות התעבורה",
    "id": "17"
  },
  {
    "title": "עצירה (כולל העמדה וחניה) בניגוד לכיוון הנסיעה",
    "symbol": 6760,
    "severity": "**",
    "type": "דמ\"ש",
    "description": "עצרת את הרכב הנ\"ל בניוד לכיוון הנסיעה, בניגוד לתקנה 72(א)(1) לתקנות התעבורה",
    "id": "18"
  },
  {
    "title": "העמדת רכב (כולל חניה) בתוך שטח הפרדה",
    "symbol": 6531,
    "severity": "**",
    "type": "דמ\"ש",
    "description": "העמדת את הרכב הנ\"ל בתוך שטח הפרדה המחלק את הדרך, בניגוד לתקנה 36(ב) לתקנות התעבורה",
    "id": "19"
  },
  {
    "title": "לוחית הזיהוי הקדמית/האחורית שתי לוחיות הזיהוי אינה/אינן נקיות",
    "symbol": 6230,
    "severity": "*",
    "type": "דמ\"ש",
    "description": "נהגת ברכב הנ\"ל כשלוחית הזיהוי הקדמית/האחורית/שתי לוחיות הזיהוי לא הייתה/היו לא נקייה/נקיות ולא ניתן היה להבחין בברור במספר הרכב, בניגוד לתקנה 165 (א) לתקנות התעבורה",
    "id": "20"
  },
  {
    "title": "לוחית הזיהוי הקדמית/האחורית/שתי לוחיות הזיהוי אינה/אינן תקינות",
    "symbol": 6230,
    "severity": "*",
    "type": "דמ\"ש",
    "description": "נהגת ברכב הנ\"ל כשלוחית הזיהוי הקדמית/האחורית/שתי לוחיות הזיהוי, אינה/אינן תקינה/תקינות, אינה/אינן נראית/נראות ממרחק 40 מטר, בניגוד לתקנה 165 (א) לתקנות התעבורה",
    "id": "21"
  },
  {
    "title": "נהיגה על מדרכה (שלא לשם חצייתה)",
    "symbol": 6402,
    "severity": "*",
    "type": "ביד\"ץ",
    "description": "נהגת ברכב הנ\"ל על המדרכה, שלא לשם חצייתה כדי להיכנס לחצרים או לצאת מהם, בניגוד לתקנה 38(א) לתקנות התעבורה",
    "id": "22"
  },
  {
    "title": "עשיית מעשה שלא כדרך, המגביל את השימוש בדרך (למעט מדרכה)",
    "symbol": 6657,
    "severity": "**",
    "type": "דמ\"ש",
    "description": "עשית ללא סמכות על-פי דין, מעשה שיש בו כדי לצמצם לסכן/ למנוע את השימוש הכללי בדרך/להקטין את מהירות הנסיעה המותרת בדרך/להפריע לתנועה החופשית, בכך ש... (פרט), בניגוד לתקנה 151 (א) לתקנות התעבורה",
    "id": "23"
  },
  {
    "title": "אי הסרת מכשול מהדרך (למעט במדרכה)",
    "symbol": 6720,
    "severity": "**",
    "type": "דמ\"ש",
    "description": "לא החזרת את מצב הדרך לקדמותו, לאחר שסיימת את המעשה שהיה בו כדי לצמצם/לסכן/למנוע את השימוש הכללי בדרך/להקטין את מהירות הנסיעה המותרת בדרך/להפריע לתנוע החופשית, בכך ש... (פרט), בניגוד לתקנה 151 (א) לתקנות התעבורה",
    "id": "24"
  },
  {
    "title": "הגורם לאחר להניח דבר העלול להטריד/לסכן/להפריע לעוברי דרך למעט במדרכה",
    "symbol": 6721,
    "severity": "**",
    "type": "דמ\"ש",
    "description": "גרמת לכך שאחר יניח על פני הדרך דבר העלול להטריד/לסכן/ להפריע, לעוברי דרך ולא סילקת אותו מיד מעל פני הדרך, בניגוד לתקנה 152 (א) לתקנות התעבורה",
    "id": "25"
  },
  {
    "title": "אי עצירה לפני המסילה בהינתן אות אזהרה",
    "symbol": 6600,
    "severity": "***",
    "type": "דמ\"ש",
    "description": " נהגת ברכב הנ\"ל ולא עצרת לפני מסילת הברזל/המשכת בנסיעה לאחר שעצרת, כשניתך אות אזהרה על התקרבות רכבת בדגל/ בעדשה אדומה מהבהבת, בניגוד לסעיף 65(1) לפקודות התעבורה",
    "id": "26"
  },
  {
    "title": "אי עצירה לפני המפגש כשהמחסום נע",
    "symbol": 6600,
    "severity": "***",
    "type": "דמ\"ש",
    "description": "נהגת ברכב הנ\"ל ולא עצרת לפני מסילת הברזל/המשכת בנסיעה לאחר שעצרת, כשהמחסום שלפני המפגש חוסם את הדרך אן חלק ממנה/ נע לקראת חסימת/פתיחת הדרך. בניגוד לסעיף 65(2) לתקנות התעבורה",
    "id": "27"
  },
  {
    "title": "אי עצירה לפני המפגש בהתקרב רכבת",
    "symbol": 6600,
    "severity": "**",
    "type": "דמ\"ש",
    "description": "נהגת ברכב הנ\"ל ולא עצרת לפני מסילת הברזל/המשכת בנסיעה לאחר שעצרת, כשרכבת מתקרבת נראית/נשמעת/משמיעה אות אזהרה בניגוד לסעיף 65(3) לפקודות התעבורה ",
    "id": "28"
  },
  {
    "title": "אי עצירה לפני המפגש, כשלידו תמרור \"עצור\"",
    "symbol": 6706,
    "severity": "**",
    "type": "ביד\"ץ",
    "description": " נהגת ברכב הנ\"ל ולא עצרת לפני מפגש מסילת ברזל שלפניו הוצב תמרור 302 המורה על עצירה, בניגוד לתקנה 56(א)(2) לפקודות התעבורה",
    "id": "29"
  },
  {
    "title": "כניסה למפגש (מסילת ברזל) כשאין אפשרות להמשיד בנסיעה",
    "symbol": 6698,
    "severity": "*",
    "type": "דמ\"ש",
    "description": "נהגת ברכב הנ\"ל ונכנסת למפגש מסילת ברזל בלי שהיה ביכולתך לעבור ולהמשיך בנסיעה ללא הפרעה, בניגוד לתקנה 65 לתקנות התעבורה",
    "id": "30"
  },
  {
    "title": "אי מילוי הוראות בעת עצירה במפגש- אוטובוס",
    "symbol": 6707,
    "severity": "*",
    "type": "דמ\"ש",
    "description": "נהגת באוטובוס הנ\"ל ובעת שעצרת לפני מפגש מסילת ברזל לפי תמרור 302, לא פתחת את הדלת הקדמית, בניגוד לתקנה 56(ב)(2) לתקנות התעבורה",
    "id": "31"
  },
  {
    "title": "נהיגה תחת השפעת סמים/אלכוהול (פסילה מנהלתית)",
    "symbol": 6372,
    "severity": "***",
    "type": "ביד\"ץ + עיכוב נהג + פתיחת תיק מצ\"ח",
    "description": "נהגת ברכב הנ\"ל בהיותך שיכור, בכך שהיית נתון תחת השפעת סמים משכרים, משקאות משכרים, בניגוד לסעיף 62(3) לפקודת התעבורה ותקנות 26(6) ו 169 ב(א) לפקודות התעבורה",
    "note": "במקרה כזה לא ירשם דו\"ח לנהג, עוצרים את הנהג ומביאים אותו לתחנת מצ\"ח הקרובה, צריך לצרף טופס למאפיינים לחשוד פירוט אופן טיפול בנהג החשוד בנהיגה תחת שכרות בעמוד 10",
    "id": "32"
  },
  {
    "title": "נהיגה תחת השפעת אלכוהול עיכוב הנהג ופתיחת תיק מצ\"ח",
    "symbol": 6373,
    "severity": "***",
    "type": "ביד\"ץ + עיכוב נהג + פתיחת תיק מצ\"ח",
    "description": "נהגת ברכב הנל הנעת את הרכב הנ\"ל בדרך במקום ציבורי בהיותך שיכור. בכך שריכוז האלכוהול של ... מילגרם במאה מיליליטר דם שנמצא בדמך עלה על המידה הקבועה, בניגוד לסעיף 62(3) לפקודת התעבורה ותקנות 62(6) ו 169 ב' לתקנות התעבורה",
    "note": "פירוט אופן טיפול בנהג החשוד בנהיגה תחת שכרות בעמוד 10",
    "id": "33"
  },
  {
    "title": "נהיגה ברכב בהיותך שיכור (אויר נשוף) עיכוב הנהג ופתיחת תיק מצ\"ח",
    "symbol": 6373,
    "severity": "***",
    "type": "ביד\"ץ + עיכוב נהג + פתיחת תיק מצ\"ח",
    "description": "נהגת ברכב הנ\"ל/הנעת את הרכב הנ\"ל בדרך/במקום ציבורי בהיותך שיכור, שבדוגמה של אויר נשוף שלך נמצא כי ריכוז האלכוהול בליטר אחד של אויר נשוף הינו ... מיקרוגרם, העולה על המידה הקבועה, בניגוד לסעיף 62(3) לתקנות התעבורה",
    "note": "פירוט אופן טיפול בנהג החשוד בנהיגה תחת שכרות בעמוד 10",
    "id": "34"
  },
  {
    "title": "סירוב להיבדק בבדיקת נשיפה/שתן דם עיקוב הנהג ופתיחת תיק מצ\"ח ",
    "symbol": 6374,
    "severity": "***",
    "type": "ביד\"ץ + עיכוב נהג + פתיחת תיק מצ\"ח",
    "description": "נהגת ברכב הנ\"ל וסירבת להיבדק על פי דרישת השוטר, בבדיקת נשיפה/למסור בדיקה של דם/שתן, לבדיקה במעבדה, בניגוד לסעיפים 62(3) 64(ד)4 וסעיף 39א לתקנות התעבורה",
    "note": "פירוט אופן טיפול בנהג החשוד בנהיגה תחת שכרות בעמוד 10",
    "id": "35"
  },
  {
    "title": "נסיעה אחורנית תוך סיכון עוברי דרך",
    "symbol": 6403,
    "severity": "**",
    "type": "ביד\"ץ",
    "description": "נהגת ברכב הנ\"ל והסעת אותו אחורנית ללא צורך תוך סיכון עוברי דרך שהיו במקום, בניגוד לתקנה 45(א) לתקנות התעבורה",
    "id": "36"
  },
  {
    "title": "נסיעה אחורנית ללא צורך",
    "symbol": 6404,
    "severity": "*",
    "type": "דמ\"ש",
    "description": "נהגת ברכב הנ\"ל והסעת אותו אחורנית ללא צורך בניגוד לתקנה 45 לתקנות התעבורה",
    "id": "37"
  },
  {
    "title": "הטרדה/ הפרעה לעוברי דרך בנסיעה אחורנית",
    "symbol": 6405,
    "severity": "*",
    "type": "דמ\"ש",
    "description": "נהגת ברכב הנ\"ל, והסעת אותו אחורנית ללא צורך וגרמת בכך להטרדה/הפרעה לעוברי דרך, בניגוד לתקנה 45(2) לתקנות התעבורה",
    "id": "38"
  },
  {
    "title": "נהיגה שלא בימין הקיצוני של כביש חד-סטרי ושל כביש דו-סטרי",
    "symbol": 8338,
    "severity": "*",
    "type": "ביד\"ץ",
    "description": "נהגת ברכב הנ\"ל שלא בצידו הימני הקיצוני של הכביש, בניגוד לתקנה 35 לת\"ת",
    "id": "39"
  },
  {
    "title": "אי שמירה על הימין בדרך צרה",
    "symbol": 6253,
    "severity": "*",
    "type": "דמ\"ש",
    "description": "נהגת ברכב הנ\"ל בדרך שאיננה רחבה במידה מספקת למעבר חופשי של שני כלי רכב מכיוונים נגדיים, ולא הימנת ככל האפשר לשפת הכביש, בניגוד לתקנה 46(א) לתקנות התעבורה",
    "id": "40"
  },
  {
    "title": "אי סימון מטען החורג לפנים ",
    "symbol": 6307,
    "severity": "**",
    "type": "דמ\"ש",
    "description": "נהגת ברכב הנ\"ל, והובלת בר מטען שחרג מחלקו הקדמי של הרכב, מבלי שהמטען סומן בקצהו החורג במשולש, בניגוד לתקנה 88 (א) לתקנות התעבורה",
    "id": "41"
  },
  {
    "title": "אי סימון מטען חורג מאחור",
    "symbol": 6307,
    "severity": "**",
    "type": "דמ\"ש",
    "description": "נהגת ברכב הנ\"ל, והובלת בן שחרג מחלקן האחורי של הרכב, מבלי שהמטען סומן בקצהו החורג במשולש, בניגוד לתקנה 88 (ב) לתקנות התעבורה",
    "id": "42"
  },
  {
    "title": "(העדר סימון ברכב הוראה (מטעם בית- ספר לנהיגה",
    "symbol": 6357,
    "severity": "**",
    "type": "דמ\"ש",
    "description": "נהגת ברכב הנ\"ל, ולא סימנת אותו מלפנים ומאחור, בסימון ההיכר שקבעה רשות רישוי, בניגוד לתקנה 230 (ב) לתקנות התעבורה",
    "id": "43"
  },
  {
    "title": "אי הסרת סימן ההיכר להוראה",
    "symbol": 6358,
    "severity": "**",
    "type": "דמ\"ש",
    "description": "נהגת ברכב הנ\"ל, כשהוא נושא עליו סימני היכר להוראת נהיגה, בזמן שלא הורית בו נהיגה, בניגוד לתקנה 230 (ג) לתקנות התעבורה",
    "id": "44"
  },
  {
    "title": "נהיגת רכב שמבנהו, ציודו ואביזריו אינם בהתאם לתקנות",
    "symbol": 6679,
    "severity": "*",
    "type": "דמ\"ש",
    "description": "נהגת ברכב הנ\"ל, כאשר מבנהו/ציודו/ אביזריו/סימונו/נשיאת מטענו לא היו בהתאם להוראות הפקודה או התקנות בכך ש... בניגוד לתקנה 27 (ב) לתקנות התעבורה",
    "id": "45"
  },
  {
    "title": "מטען רחב ללא היתר",
    "symbol": 6673,
    "severity": "*",
    "type": "דמ\"ש",
    "description": "נהגת ברכב הנ\"ל והובלת מטען שרוחבו היה... מי בלא שקיבלת לכך היתר מקצין משטרה, בניגוד לתקנה 85(ג)(3) לתקנות התעבורה",
    "id": "46"
  },
  {
    "title": "מטען רחב - שלא בתאם לתנאי ההיתר",
    "symbol": 6672,
    "severity": "*",
    "type": "דמ\"ש",
    "description": "נהגת ברכב הנ\"ל והובלת מטען שרוחבו היה... מ' שלא בהתאם לתנאי ההיתר שקיבלת לכך מאת קצין במשטרה בכך ש... בעוד שבהיתר נכתב... בניגוד לתקנה 85(ג)(3) לתקנות התעבורה",
    "id": "47"
  },
  {
    "title": "אחריות בעל הרכב לנהיגת רכב שנאסר בשימוש",
    "symbol": 6671,
    "severity": "***",
    "type": "ביד\"ץ + עיכוב נהג + פתיחת תיק מצ\"ח",
    "description": " בהיותך בעל הרכב הנ\"ל/בעל השליטה ברכב הנ\"ל, שנמסרה לגביך הודעת איסור שימוש, הרשת לאחר לנהוג שלא לשם נסיעה לתיקונו, או למלא התנאים בהודעה הנ\"ל, בניגוד לתקנה 308 (ד) ותקנה 162 (א) לת\"ת.",
    "id": "48"
  },
  {
    "title": "העלאת/הורדת נוסע בדרך מהירה",
    "symbol": 6661,
    "severity": "**",
    "type": "דמ\"ש",
    "description": "נהגת ברכב הנ\"ל, בדרך מהירה, ועצרת רכבך לשם העלאת/הורדת נוסע, בניגוד לתקנה 69 (ג) לתקנות התעבורה",
    "id": "49"
  },
  {
    "title": "נוסע העולה לרכב/יורד מהרכב בתנועה",
    "symbol": 6660,
    "severity": "**",
    "type": "דמ\"ש",
    "description": "בתנועה עלית לרכב/ירדת מהרכב הנ\"ל, בזמן שהרכב נע,בניגוד לתקנה 81(1) לתקנות התעבורה",
    "id": "50"
  },
  {
    "title": "נהג המניח לנוסע לעלות לרכב/לרדת מהרכב בתנועה",
    "symbol": 6272,
    "severity": "**",
    "type": "דמ\"ש",
    "description": "נהגת ברכב הנ\"ל, והנחת לנוסע לעלות לרכב/לרדת מהרכב, בזמן שהרכב נע, בניגוד לתקנה 81(1) לתקנות התעבורה",
    "id": "51"
  },
  {
    "title": "עקיפה מימין",
    "symbol": 6410,
    "severity": "*",
    "type": "ביד\"ץ",
    "description": "נהגת ברכב הנ\"ל ועקפת מצד רמרך רכב אחר הנע בכביש, בניגוד לתקנה 47(א) לתקנות התעבורה",
    "id": "52"
  },
  {
    "title": "עקיפה כשהדרך לא פנויה",
    "symbol": 6392,
    "severity": "***",
    "type": "ביד\"ץ",
    "description": "נהגת ברכב הנ\"ל ועקפת רכב אחר כשהדרך לא הייתה פנויה במרחק מספיק כדי לאפשר ביצוע עקיפה בבטחה, ובכך גרמת לסיכון נסיעתו של רכב אחר, בניגוד לתקנה 47(ד) לתקנות התעבורה",
    "id": "53"
  },
  {
    "title": "עקיפה בראות לקויה או כששדה הראייה חסום או מוגבל",
    "symbol": 6708,
    "severity": "**",
    "type": "ביד\"ץ",
    "description": "נהגת ברכב הנ\"ל ועקפת רכב/וניסית לעקוף רכב/וסטית עם רכבך שמאלה/ ימינה כדי לעקוף רכב/בעל-חיים, כאשר הראות לקוייה/שדה הראייה חסום/שדה הראייה מוגבל, בניגוד לתקנה 47(ה)(1) לתקנות התעבורה",
    "id": "54"
  },
  {
    "title": "ניסיון לעקיפה/סטייה לעקיפה/עקיפה אחרי תמך מפגש מסילת ברזל (132)",
    "symbol": 6248,
    "severity": "*",
    "type": "ביד\"ץ",
    "description": "נהגת ברכב הנ\"ל ועקפת/ניסית לעקוף/סטית כדי לעקוף רכב אחר/בהימצאך אחרי תמרור 132 ולפני מפגש מסילת ברזל, בניגוד לתקנה 47(ה)(2) לתקנות התעבורה",
    "id": "55"
  },
  {
    "title": "עקיפה לפני מעבר חצייה",
    "symbol": 6245,
    "severity": "**",
    "type": "ביד\"ץ",
    "description": "נהגת ברכב הנ\"ל ועקפת רכב וניסית לעקוף רכב/וסטית עם רכבך שמאלה כדי לעקוף רכב בהתקרבך אל מעבר החצייה להולכי רגל המסומן על פני הכביש/על-ידי תמרור המציין מקום מעבר חצייה להולכי רגל בניגוד לתקנה 47(ה)(3) לתקנות התעבורה",
    "id": "56"
  }
]